{"providers":[{"type":"space","advances":{" ":4}},{"type":"bitmap","file":"mcc:_fonts/minecraft_bone_block.png","chars":[""],"ascent":24,"height":48},{"type":"bitmap","file":"mcc:_fonts/minecraft_brewing_stand.png","chars":[""],"ascent":24,"height":48},{"type":"bitmap","file":"mcc:_fonts/minecraft_cooked_porkchop.png","chars":[""],"ascent":24,"height":48},{"type":"bitmap","file":"mcc:_fonts/minecraft_cracked_nether_bricks.png","chars":[""],"ascent":24,"height":48},{"type":"bitmap","file":"mcc:_fonts/minecraft_crimson_hyphae.png","chars":[""],"ascent":24,"height":48},{"type":"bitmap","file":"mcc:_fonts/minecraft_diamond_hoe.png","chars":[""],"ascent":24,"height":48},{"type":"bitmap","file":"mcc:_fonts/minecraft_ender_eye.png","chars":[""],"ascent":24,"height":48},{"type":"bitmap","file":"mcc:_fonts/minecraft_golden_chestplate.png","chars":[""],"ascent":24,"height":48},{"type":"bitmap","file":"mcc:_fonts/minecraft_golden_hoe.png","chars":[""],"ascent":24,"height":48},{"type":"bitmap","file":"mcc:_fonts/minecraft_item_frame.png","chars":[""],"ascent":24,"height":48},{"type":"bitmap","file":"mcc:_fonts/minecraft_leather_boots.png","chars":[""],"ascent":24,"height":48},{"type":"bitmap","file":"mcc:_fonts/minecraft_leather_chestplate.png","chars":[""],"ascent":24,"height":48},{"type":"bitmap","file":"mcc:_fonts/minecraft_mushroom_stew.png","chars":[""],"ascent":24,"height":48},{"type":"bitmap","file":"mcc:_fonts/minecraft_netherite_scrap.png","chars":[""],"ascent":24,"height":48},{"type":"bitmap","file":"mcc:_fonts/minecraft_polished_basalt.png","chars":[""],"ascent":24,"height":48},{"type":"bitmap","file":"mcc:_fonts/minecraft_red_nether_brick_wall.png","chars":[""],"ascent":24,"height":48},{"type":"bitmap","file":"mcc:_fonts/minecraft_red_nether_bricks.png","chars":[""],"ascent":24,"height":48},{"type":"bitmap","file":"mcc:_fonts/minecraft_smithing_table.png","chars":[""],"ascent":24,"height":48},{"type":"bitmap","file":"mcc:_fonts/minecraft_soul_torch.png","chars":[""],"ascent":24,"height":48},{"type":"bitmap","file":"mcc:_fonts/minecraft_stone_hoe.png","chars":[""],"ascent":24,"height":48},{"type":"bitmap","file":"mcc:_fonts/minecraft_stone_sword.png","chars":[""],"ascent":24,"height":48},{"type":"bitmap","file":"mcc:_fonts/minecraft_trapped_chest.png","chars":[""],"ascent":24,"height":48},{"type":"bitmap","file":"mcc:_fonts/minecraft_warped_fence_gate.png","chars":[""],"ascent":24,"height":48},{"type":"bitmap","file":"mcc:_fonts/minecraft_warped_fungus_on_a_stick.png","chars":[""],"ascent":24,"height":48},{"type":"bitmap","file":"mcc:_fonts/minecraft_wooden_hoe.png","chars":[""],"ascent":24,"height":48}]}