{"providers":[{"type":"space","advances":{" ":4}},{"type":"bitmap","file":"mcc:_fonts/accept.png","chars":["¯ÇÇ"],"ascent":-66,"height":8},{"type":"bitmap","file":"mcc:_fonts/accessory_small.png","chars":["¯Çü"],"ascent":-66,"height":8},{"type":"bitmap","file":"mcc:_fonts/ace_race/elytra.png","chars":["¯Çé"],"ascent":-66,"height":8},{"type":"bitmap","file":"mcc:_fonts/ace_race/grace.png","chars":["¯Çâ"],"ascent":-66,"height":8},{"type":"bitmap","file":"mcc:_fonts/ace_race/split_down.png","chars":["¯Çä"],"ascent":-66,"height":8},{"type":"bitmap","file":"mcc:_fonts/ace_race/split_up.png","chars":["¯Çà"],"ascent":-66,"height":8},{"type":"bitmap","file":"mcc:_fonts/ace_race/trident.png","chars":["¯Çå"],"ascent":-66,"height":8},{"type":"bitmap","file":"mcc:_fonts/ace_race/wind_charge.png","chars":["¯Çç"],"ascent":-66,"height":8},{"type":"bitmap","file":"mcc:_fonts/action_bar_champion.png","chars":["¯Çê"],"ascent":-66,"height":80},{"type":"bitmap","file":"mcc:_fonts/action_bar_champion_medal.png","chars":["¯Çë"],"ascent":-66,"height":80},{"type":"bitmap","file":"mcc:_fonts/action_bar_currency.png","chars":["¯Çè"],"ascent":-66,"height":80},{"type":"bitmap","file":"mcc:_fonts/alex.png","chars":["¯Çï"],"ascent":-66,"height":8},{"type":"bitmap","file":"mcc:_fonts/arrow.png","chars":["¯Çî"],"ascent":-66,"height":8},{"type":"bitmap","file":"mcc:_fonts/arrow_down.png","chars":["¯Çì"],"ascent":-66,"height":32},{"type":"bitmap","file":"mcc:_fonts/arrow_up.png","chars":["¯ÇÄ"],"ascent":-49,"height":32},{"type":"bitmap","file":"mcc:_fonts/assists.png","chars":["¯ÇÅ"],"ascent":-66,"height":8},{"type":"bitmap","file":"mcc:_fonts/attunement_crystal.png","chars":["¯ÇÉ"],"ascent":-66,"height":8},{"type":"bitmap","file":"mcc:_fonts/aura_small.png","chars":["¯Çæ"],"ascent":-66,"height":8},{"type":"bitmap","file":"mcc:_fonts/back_small.png","chars":["¯ÇÆ"],"ascent":-66,"height":8},{"type":"bitmap","file":"mcc:_fonts/badges.png","chars":["¯Çô"],"ascent":-66,"height":16},{"type":"bitmap","file":"mcc:_fonts/badges_small.png","chars":["¯Çö"],"ascent":-66,"height":8},{"type":"bitmap","file":"mcc:_fonts/battle_pass_small.png","chars":["¯Çò"],"ascent":-66,"height":8},{"type":"bitmap","file":"mcc:_fonts/board_tile.png","chars":["¯Çû"],"ascent":-66,"height":8},{"type":"bitmap","file":"mcc:_fonts/bottle.png","chars":["¯Çù"],"ascent":-66,"height":7},{"type":"bitmap","file":"mcc:_fonts/breakdown.png","chars":["¯Çÿ"],"ascent":-66,"height":8},{"type":"bitmap","file":"mcc:_fonts/cancel.png","chars":["¯ÇÖ"],"ascent":-66,"height":8},{"type":"bitmap","file":"mcc:_fonts/castle.png","chars":["¯ÇÜ"],"ascent":-66,"height":8},{"type":"bitmap","file":"mcc:_fonts/championscore.png","chars":["¯Çø"],"ascent":-66,"height":8},{"type":"bitmap","file":"mcc:_fonts/championscore_legacy.png","chars":["¯Ç£"],"ascent":-66,"height":8},{"type":"bitmap","file":"mcc:_fonts/charge.png","chars":["¯ÇØ"],"ascent":-66,"height":7},{"type":"bitmap","file":"mcc:_fonts/chat_buttons/accept.png","chars":["¯Ç×"],"ascent":-66,"height":7},{"type":"bitmap","file":"mcc:_fonts/chat_buttons/add_them_back.png","chars":["¯Çƒ"],"ascent":-66,"height":7},{"type":"bitmap","file":"mcc:_fonts/chat_buttons/decline.png","chars":["¯Çá"],"ascent":-66,"height":7},{"type":"bitmap","file":"mcc:_fonts/chat_buttons/ignore.png","chars":["¯Çí"],"ascent":-66,"height":7},{"type":"bitmap","file":"mcc:_fonts/chat_channel/disguised.png","chars":["¯Çó"],"ascent":-126,"height":9},{"type":"bitmap","file":"mcc:_fonts/chat_channel/local.png","chars":["¯Çú"],"ascent":-126,"height":9},{"type":"bitmap","file":"mcc:_fonts/chat_channel/party.png","chars":["¯Çñ"],"ascent":-126,"height":9},{"type":"bitmap","file":"mcc:_fonts/chat_channel/plobby.png","chars":["¯ÇÑ"],"ascent":-126,"height":9},{"type":"bitmap","file":"mcc:_fonts/chat_channel/staff.png","chars":["¯Çª"],"ascent":-126,"height":9},{"type":"bitmap","file":"mcc:_fonts/chat_channel/team.png","chars":["¯Çº"],"ascent":-126,"height":9},{"type":"bitmap","file":"mcc:_fonts/chat_channel/vanished.png","chars":["¯Ç¿"],"ascent":-126,"height":9},{"type":"bitmap","file":"mcc:_fonts/chicken.png","chars":["¯Ç®"],"ascent":-66,"height":8},{"type":"bitmap","file":"mcc:_fonts/chicken_offset_53.png","chars":["¯Ç¬"],"ascent":-118,"height":8},{"type":"bitmap","file":"mcc:_fonts/chroma_pack_small.png","chars":["¯Ç½"],"ascent":-66,"height":8},{"type":"bitmap","file":"mcc:_fonts/circle_empty.png","chars":["¯Ç¼"],"ascent":-66,"height":8},{"type":"bitmap","file":"mcc:_fonts/circle_full.png","chars":["¯Ç¡"],"ascent":-66,"height":8},{"type":"bitmap","file":"mcc:_fonts/click_action_left.png","chars":["¯Ç«"],"ascent":-66,"height":7},{"type":"bitmap","file":"mcc:_fonts/click_action_right.png","chars":["¯Ç»"],"ascent":-66,"height":7},{"type":"bitmap","file":"mcc:_fonts/click_action_shift.png","chars":["¯Ç░"],"ascent":-66,"height":7},{"type":"bitmap","file":"mcc:_fonts/coin.png","chars":["¯Ç▒"],"ascent":-66,"height":8},{"type":"bitmap","file":"mcc:_fonts/coin_small.png","chars":["¯Ç▓"],"ascent":-66,"height":8},{"type":"bitmap","file":"mcc:_fonts/coin_small_v1.png","chars":["¯Ç│"],"ascent":-66,"height":8},{"type":"bitmap","file":"mcc:_fonts/coin_token.png","chars":["¯Ç┤"],"ascent":-66,"height":16},{"type":"bitmap","file":"mcc:_fonts/coin_token_small.png","chars":["¯ÇÁ"],"ascent":-66,"height":8},{"type":"bitmap","file":"mcc:_fonts/coin_token_v2.png","chars":["¯ÇÂ"],"ascent":-66,"height":16},{"type":"bitmap","file":"mcc:_fonts/coin_token_v3.png","chars":["¯ÇÀ"],"ascent":-66,"height":16},{"type":"bitmap","file":"mcc:_fonts/coin_token_v4.png","chars":["¯Ç©"],"ascent":-66,"height":16},{"type":"bitmap","file":"mcc:_fonts/crafting.png","chars":["¯Ç╣"],"ascent":-66,"height":8},{"type":"bitmap","file":"mcc:_fonts/crown.png","chars":["¯Ç║"],"ascent":-66,"height":8},{"type":"bitmap","file":"mcc:_fonts/crown_small.png","chars":["¯Ç╗"],"ascent":-66,"height":8},{"type":"bitmap","file":"mcc:_fonts/default.png","chars":["¯Ç╝"],"ascent":-66,"height":20},{"type":"bitmap","file":"mcc:_fonts/disconnect.png","chars":["¯Ç¢"],"ascent":-72,"height":8},{"type":"bitmap","file":"mcc:_fonts/disguise.png","chars":["¯Ç¥"],"ascent":-66,"height":8},{"type":"bitmap","file":"mcc:_fonts/dodgebolt/arrow_display.png","chars":["¯Ç┐"],"ascent":-33,"height":40},{"type":"bitmap","file":"mcc:_fonts/dome.png","chars":["¯üÇ"],"ascent":-66,"height":8},{"type":"bitmap","file":"mcc:_fonts/dryness.png","chars":["¯üü"],"ascent":-66,"height":9},{"type":"bitmap","file":"mcc:_fonts/dynaball/tnt_display.png","chars":["¯üé"],"ascent":-33,"height":40},{"type":"bitmap","file":"mcc:_fonts/dynaball/tnt_notif.png","chars":["¯üâ"],"ascent":-66,"height":8},{"type":"bitmap","file":"mcc:_fonts/elytra.png","chars":["¯üä"],"ascent":-66,"height":8},{"type":"bitmap","file":"mcc:_fonts/emojis/alien.png","chars":["¯üà"],"ascent":-66,"height":8},{"type":"bitmap","file":"mcc:_fonts/emojis/angry.png","chars":["¯üå"],"ascent":-66,"height":8},{"type":"bitmap","file":"mcc:_fonts/emojis/aqua.png","chars":["¯üç"],"ascent":-66,"height":8},{"type":"bitmap","file":"mcc:_fonts/emojis/blue.png","chars":["¯üê"],"ascent":-66,"height":8},{"type":"bitmap","file":"mcc:_fonts/emojis/burger.png","chars":["¯üë"],"ascent":-66,"height":8},{"type":"bitmap","file":"mcc:_fonts/emojis/chicken.png","chars":["¯üè"],"ascent":-66,"height":8},{"type":"bitmap","file":"mcc:_fonts/emojis/clown.png","chars":["¯üï"],"ascent":-66,"height":8},{"type":"bitmap","file":"mcc:_fonts/emojis/coins.png","chars":["¯üî"],"ascent":-66,"height":8},{"type":"bitmap","file":"mcc:_fonts/emojis/crown.png","chars":["¯üì"],"ascent":-66,"height":8},{"type":"bitmap","file":"mcc:_fonts/emojis/cyan.png","chars":["¯üÄ"],"ascent":-66,"height":8},{"type":"bitmap","file":"mcc:_fonts/emojis/eyes.png","chars":["¯üÅ"],"ascent":-66,"height":8},{"type":"bitmap","file":"mcc:_fonts/emojis/fearful.png","chars":["¯üÉ"],"ascent":-66,"height":8},{"type":"bitmap","file":"mcc:_fonts/emojis/flushed.png","chars":["¯üæ"],"ascent":-66,"height":8},{"type":"bitmap","file":"mcc:_fonts/emojis/green.png","chars":["¯üÆ"],"ascent":-66,"height":8},{"type":"bitmap","file":"mcc:_fonts/emojis/grimacing.png","chars":["¯üô"],"ascent":-66,"height":8},{"type":"bitmap","file":"mcc:_fonts/emojis/grin.png","chars":["¯üö"],"ascent":-66,"height":8},{"type":"bitmap","file":"mcc:_fonts/emojis/heart.png","chars":["¯üò"],"ascent":-66,"height":8},{"type":"bitmap","file":"mcc:_fonts/emojis/heart_black.png","chars":["¯üû"],"ascent":-66,"height":8},{"type":"bitmap","file":"mcc:_fonts/emojis/heart_blue.png","chars":["¯üù"],"ascent":-66,"height":8},{"type":"bitmap","file":"mcc:_fonts/emojis/heart_eyes.png","chars":["¯üÿ"],"ascent":-66,"height":8},{"type":"bitmap","file":"mcc:_fonts/emojis/heart_green.png","chars":["¯üÖ"],"ascent":-66,"height":8},{"type":"bitmap","file":"mcc:_fonts/emojis/heart_orange.png","chars":["¯üÜ"],"ascent":-66,"height":8},{"type":"bitmap","file":"mcc:_fonts/emojis/heart_pink.png","chars":["¯üø"],"ascent":-66,"height":8},{"type":"bitmap","file":"mcc:_fonts/emojis/heart_purple.png","chars":["¯ü£"],"ascent":-66,"height":8},{"type":"bitmap","file":"mcc:_fonts/emojis/heart_white.png","chars":["¯üØ"],"ascent":-66,"height":8},{"type":"bitmap","file":"mcc:_fonts/emojis/heart_yellow.png","chars":["¯ü×"],"ascent":-66,"height":8},{"type":"bitmap","file":"mcc:_fonts/emojis/hexapus.png","chars":["¯üƒ"],"ascent":-66,"height":8},{"type":"bitmap","file":"mcc:_fonts/emojis/imp.png","chars":["¯üá"],"ascent":-66,"height":8},{"type":"bitmap","file":"mcc:_fonts/emojis/joy.png","chars":["¯üí"],"ascent":-66,"height":8},{"type":"bitmap","file":"mcc:_fonts/emojis/kekw.png","chars":["¯üó"],"ascent":-66,"height":8},{"type":"bitmap","file":"mcc:_fonts/emojis/laughing.png","chars":["¯üú"],"ascent":-66,"height":8},{"type":"bitmap","file":"mcc:_fonts/emojis/lime.png","chars":["¯üñ"],"ascent":-66,"height":8},{"type":"bitmap","file":"mcc:_fonts/emojis/mcc_angry.png","chars":["¯üÑ"],"ascent":-66,"height":8},{"type":"bitmap","file":"mcc:_fonts/emojis/mcc_smile.png","chars":["¯üª"],"ascent":-66,"height":8},{"type":"bitmap","file":"mcc:_fonts/emojis/music_note.png","chars":["¯üº"],"ascent":-66,"height":8},{"type":"bitmap","file":"mcc:_fonts/emojis/nerd.png","chars":["¯ü¿"],"ascent":-66,"height":8},{"type":"bitmap","file":"mcc:_fonts/emojis/neutral.png","chars":["¯ü®"],"ascent":-66,"height":8},{"type":"bitmap","file":"mcc:_fonts/emojis/noxcrew.png","chars":["¯ü¬"],"ascent":-66,"height":8},{"type":"bitmap","file":"mcc:_fonts/emojis/orange.png","chars":["¯ü½"],"ascent":-66,"height":8},{"type":"bitmap","file":"mcc:_fonts/emojis/pensive.png","chars":["¯ü¼"],"ascent":-66,"height":8},{"type":"bitmap","file":"mcc:_fonts/emojis/pink.png","chars":["¯ü¡"],"ascent":-66,"height":8},{"type":"bitmap","file":"mcc:_fonts/emojis/point_left.png","chars":["¯ü«"],"ascent":-66,"height":8},{"type":"bitmap","file":"mcc:_fonts/emojis/point_right.png","chars":["¯ü»"],"ascent":-66,"height":8},{"type":"bitmap","file":"mcc:_fonts/emojis/purple.png","chars":["¯ü░"],"ascent":-66,"height":8},{"type":"bitmap","file":"mcc:_fonts/emojis/red.png","chars":["¯ü▒"],"ascent":-66,"height":8},{"type":"bitmap","file":"mcc:_fonts/emojis/scream.png","chars":["¯ü▓"],"ascent":-66,"height":8},{"type":"bitmap","file":"mcc:_fonts/emojis/skull.png","chars":["¯ü│"],"ascent":-66,"height":8},{"type":"bitmap","file":"mcc:_fonts/emojis/smile.png","chars":["¯ü┤"],"ascent":-66,"height":8},{"type":"bitmap","file":"mcc:_fonts/emojis/sob.png","chars":["¯üÁ"],"ascent":-66,"height":8},{"type":"bitmap","file":"mcc:_fonts/emojis/sunglasses.png","chars":["¯üÂ"],"ascent":-66,"height":8},{"type":"bitmap","file":"mcc:_fonts/emojis/surprised.png","chars":["¯üÀ"],"ascent":-66,"height":8},{"type":"bitmap","file":"mcc:_fonts/emojis/sus.png","chars":["¯ü©"],"ascent":-66,"height":8},{"type":"bitmap","file":"mcc:_fonts/emojis/sweat_smile.png","chars":["¯ü╣"],"ascent":-66,"height":8},{"type":"bitmap","file":"mcc:_fonts/emojis/thinking.png","chars":["¯ü║"],"ascent":-66,"height":8},{"type":"bitmap","file":"mcc:_fonts/emojis/thumbs_down.png","chars":["¯ü╗"],"ascent":-66,"height":8},{"type":"bitmap","file":"mcc:_fonts/emojis/thumbs_up.png","chars":["¯ü╝"],"ascent":-66,"height":8},{"type":"bitmap","file":"mcc:_fonts/emojis/tongue_out.png","chars":["¯ü¢"],"ascent":-66,"height":8},{"type":"bitmap","file":"mcc:_fonts/emojis/trophy.png","chars":["¯ü¥"],"ascent":-66,"height":8},{"type":"bitmap","file":"mcc:_fonts/emojis/weary.png","chars":["¯ü┐"],"ascent":-66,"height":8},{"type":"bitmap","file":"mcc:_fonts/emojis/winking_tongue.png","chars":["¯éÇ"],"ascent":-66,"height":8},{"type":"bitmap","file":"mcc:_fonts/emojis/yellow.png","chars":["¯éü"],"ascent":-66,"height":8},{"type":"bitmap","file":"mcc:_fonts/empty_box.png","chars":["¯éé"],"ascent":-66,"height":8},{"type":"bitmap","file":"mcc:_fonts/empty_flag.png","chars":["¯éâ"],"ascent":-66,"height":8},{"type":"bitmap","file":"mcc:_fonts/finish_flag.png","chars":["¯éä"],"ascent":-66,"height":8},{"type":"bitmap","file":"mcc:_fonts/game_icons/game_ace_race.png","chars":["¯éà"],"ascent":-57,"height":16},{"type":"bitmap","file":"mcc:_fonts/game_icons/game_ace_race_expanded.png","chars":["¯éå"],"ascent":-49,"height":32},{"type":"bitmap","file":"mcc:_fonts/game_icons/game_ace_race_small.png","chars":["¯éç"],"ascent":-66,"height":8},{"type":"bitmap","file":"mcc:_fonts/game_icons/game_battle_box.png","chars":["¯éê"],"ascent":-57,"height":16},{"type":"bitmap","file":"mcc:_fonts/game_icons/game_battle_box_expanded.png","chars":["¯éë"],"ascent":-49,"height":32},{"type":"bitmap","file":"mcc:_fonts/game_icons/game_battle_box_small.png","chars":["¯éè"],"ascent":-66,"height":8},{"type":"bitmap","file":"mcc:_fonts/game_icons/game_bingo_but_fast.png","chars":["¯éï"],"ascent":-57,"height":16},{"type":"bitmap","file":"mcc:_fonts/game_icons/game_bingo_but_fast_expanded.png","chars":["¯éî"],"ascent":-49,"height":32},{"type":"bitmap","file":"mcc:_fonts/game_icons/game_bingo_but_fast_small.png","chars":["¯éì"],"ascent":-66,"height":8},{"type":"bitmap","file":"mcc:_fonts/game_icons/game_build_mart.png","chars":["¯éÄ"],"ascent":-57,"height":16},{"type":"bitmap","file":"mcc:_fonts/game_icons/game_build_mart_expanded.png","chars":["¯éÅ"],"ascent":-49,"height":32},{"type":"bitmap","file":"mcc:_fonts/game_icons/game_build_mart_small.png","chars":["¯éÉ"],"ascent":-66,"height":8},{"type":"bitmap","file":"mcc:_fonts/game_icons/game_dodgebolt.png","chars":["¯éæ"],"ascent":-57,"height":16},{"type":"bitmap","file":"mcc:_fonts/game_icons/game_dodgebolt_expanded.png","chars":["¯éÆ"],"ascent":-49,"height":32},{"type":"bitmap","file":"mcc:_fonts/game_icons/game_dodgebolt_small.png","chars":["¯éô"],"ascent":-66,"height":8},{"type":"bitmap","file":"mcc:_fonts/game_icons/game_dynaball.png","chars":["¯éö"],"ascent":-57,"height":16},{"type":"bitmap","file":"mcc:_fonts/game_icons/game_dynaball_expanded.png","chars":["¯éò"],"ascent":-49,"height":32},{"type":"bitmap","file":"mcc:_fonts/game_icons/game_dynaball_small.png","chars":["¯éû"],"ascent":-66,"height":8},{"type":"bitmap","file":"mcc:_fonts/game_icons/game_grid_runners.png","chars":["¯éù"],"ascent":-57,"height":16},{"type":"bitmap","file":"mcc:_fonts/game_icons/game_grid_runners_expanded.png","chars":["¯éÿ"],"ascent":-49,"height":32},{"type":"bitmap","file":"mcc:_fonts/game_icons/game_grid_runners_small.png","chars":["¯éÖ"],"ascent":-66,"height":8},{"type":"bitmap","file":"mcc:_fonts/game_icons/game_hole_in_the_wall.png","chars":["¯éÜ"],"ascent":-57,"height":16},{"type":"bitmap","file":"mcc:_fonts/game_icons/game_hole_in_the_wall_expanded.png","chars":["¯éø"],"ascent":-49,"height":32},{"type":"bitmap","file":"mcc:_fonts/game_icons/game_hole_in_the_wall_small.png","chars":["¯é£"],"ascent":-66,"height":8},{"type":"bitmap","file":"mcc:_fonts/game_icons/game_meltdown.png","chars":["¯éØ"],"ascent":-57,"height":16},{"type":"bitmap","file":"mcc:_fonts/game_icons/game_meltdown_expanded.png","chars":["¯é×"],"ascent":-49,"height":32},{"type":"bitmap","file":"mcc:_fonts/game_icons/game_meltdown_small.png","chars":["¯éƒ"],"ascent":-66,"height":8},{"type":"bitmap","file":"mcc:_fonts/game_icons/game_parkour_tag.png","chars":["¯éá"],"ascent":-57,"height":16},{"type":"bitmap","file":"mcc:_fonts/game_icons/game_parkour_tag_expanded.png","chars":["¯éí"],"ascent":-49,"height":32},{"type":"bitmap","file":"mcc:_fonts/game_icons/game_parkour_tag_small.png","chars":["¯éó"],"ascent":-66,"height":8},{"type":"bitmap","file":"mcc:_fonts/game_icons/game_parkour_warrior.png","chars":["¯éú"],"ascent":-57,"height":16},{"type":"bitmap","file":"mcc:_fonts/game_icons/game_parkour_warrior_expanded.png","chars":["¯éñ"],"ascent":-49,"height":32},{"type":"bitmap","file":"mcc:_fonts/game_icons/game_parkour_warrior_small.png","chars":["¯éÑ"],"ascent":-66,"height":8},{"type":"bitmap","file":"mcc:_fonts/game_icons/game_parkour_warrior_solo.png","chars":["¯éª"],"ascent":-57,"height":16},{"type":"bitmap","file":"mcc:_fonts/game_icons/game_parkour_warrior_solo_small.png","chars":["¯éº"],"ascent":-57,"height":16},{"type":"bitmap","file":"mcc:_fonts/game_icons/game_railroad_rush.png","chars":["¯é¿"],"ascent":-57,"height":16},{"type":"bitmap","file":"mcc:_fonts/game_icons/game_railroad_rush_small.png","chars":["¯é®"],"ascent":-66,"height":8},{"type":"bitmap","file":"mcc:_fonts/game_icons/game_rocket_spleef.png","chars":["¯é¬"],"ascent":-57,"height":16},{"type":"bitmap","file":"mcc:_fonts/game_icons/game_rocket_spleef_expanded.png","chars":["¯é½"],"ascent":-49,"height":32},{"type":"bitmap","file":"mcc:_fonts/game_icons/game_rocket_spleef_small.png","chars":["¯é¼"],"ascent":-66,"height":8},{"type":"bitmap","file":"mcc:_fonts/game_icons/game_sands_of_time.png","chars":["¯é¡"],"ascent":-57,"height":16},{"type":"bitmap","file":"mcc:_fonts/game_icons/game_sands_of_time_expanded.png","chars":["¯é«"],"ascent":-49,"height":32},{"type":"bitmap","file":"mcc:_fonts/game_icons/game_sands_of_time_small.png","chars":["¯é»"],"ascent":-66,"height":8},{"type":"bitmap","file":"mcc:_fonts/game_icons/game_sky_battle.png","chars":["¯é░"],"ascent":-57,"height":16},{"type":"bitmap","file":"mcc:_fonts/game_icons/game_sky_battle_expanded.png","chars":["¯é▒"],"ascent":-49,"height":32},{"type":"bitmap","file":"mcc:_fonts/game_icons/game_sky_battle_small.png","chars":["¯é▓"],"ascent":-66,"height":8},{"type":"bitmap","file":"mcc:_fonts/game_icons/game_sky_battle_water_fight.png","chars":["¯é│"],"ascent":-57,"height":16},{"type":"bitmap","file":"mcc:_fonts/game_icons/game_sky_battle_water_fight_small.png","chars":["¯é┤"],"ascent":-66,"height":8},{"type":"bitmap","file":"mcc:_fonts/game_icons/game_skyblockle.png","chars":["¯éÁ"],"ascent":-57,"height":16},{"type":"bitmap","file":"mcc:_fonts/game_icons/game_skyblockle_expanded.png","chars":["¯éÂ"],"ascent":-49,"height":32},{"type":"bitmap","file":"mcc:_fonts/game_icons/game_skyblockle_small.png","chars":["¯éÀ"],"ascent":-66,"height":8},{"type":"bitmap","file":"mcc:_fonts/game_icons/game_sumo.png","chars":["¯é©"],"ascent":-57,"height":16},{"type":"bitmap","file":"mcc:_fonts/game_icons/game_sumo_small.png","chars":["¯é╣"],"ascent":-66,"height":8},{"type":"bitmap","file":"mcc:_fonts/game_icons/game_survival_games.png","chars":["¯é║"],"ascent":-57,"height":16},{"type":"bitmap","file":"mcc:_fonts/game_icons/game_survival_games_expanded.png","chars":["¯é╗"],"ascent":-49,"height":32},{"type":"bitmap","file":"mcc:_fonts/game_icons/game_survival_games_small.png","chars":["¯é╝"],"ascent":-66,"height":8},{"type":"bitmap","file":"mcc:_fonts/game_icons/game_tgttos.png","chars":["¯é¢"],"ascent":-57,"height":16},{"type":"bitmap","file":"mcc:_fonts/game_icons/game_tgttos_expanded.png","chars":["¯é¥"],"ascent":-49,"height":32},{"type":"bitmap","file":"mcc:_fonts/game_icons/game_tgttos_small.png","chars":["¯é┐"],"ascent":-66,"height":8},{"type":"bitmap","file":"mcc:_fonts/game_icons/game_tgttosawaf.png","chars":["¯âÇ"],"ascent":-57,"height":16},{"type":"bitmap","file":"mcc:_fonts/game_icons/game_tgttosawaf_expanded.png","chars":["¯âü"],"ascent":-49,"height":32},{"type":"bitmap","file":"mcc:_fonts/game_icons/game_tgttosawaf_small.png","chars":["¯âé"],"ascent":-66,"height":8},{"type":"bitmap","file":"mcc:_fonts/game_icons/island_main.png","chars":["¯ââ"],"ascent":-57,"height":16},{"type":"bitmap","file":"mcc:_fonts/game_icons/island_main_expanded.png","chars":["¯âä"],"ascent":-49,"height":32},{"type":"bitmap","file":"mcc:_fonts/game_icons/island_main_small.png","chars":["¯âà"],"ascent":-66,"height":8},{"type":"bitmap","file":"mcc:_fonts/game_titles/battle_box.png","chars":["¯âå"],"ascent":-66,"height":32},{"type":"bitmap","file":"mcc:_fonts/game_titles/hole_in_the_wall.png","chars":["¯âç"],"ascent":-66,"height":34},{"type":"bitmap","file":"mcc:_fonts/game_titles/sky_battle.png","chars":["¯âê"],"ascent":-66,"height":28},{"type":"bitmap","file":"mcc:_fonts/game_titles/tgttos.png","chars":["¯âë"],"ascent":-66,"height":27},{"type":"bitmap","file":"mcc:_fonts/gem.png","chars":["¯âè"],"ascent":-66,"height":8},{"type":"bitmap","file":"mcc:_fonts/gem_small.png","chars":["¯âï"],"ascent":-66,"height":8},{"type":"bitmap","file":"mcc:_fonts/glow_config.png","chars":["¯âî"],"ascent":-66,"height":16},{"type":"bitmap","file":"mcc:_fonts/hat_small.png","chars":["¯âì"],"ascent":-66,"height":8},{"type":"bitmap","file":"mcc:_fonts/header_icons/crafting.png","chars":["¯âÄ"],"ascent":-25,"height":48},{"type":"bitmap","file":"mcc:_fonts/header_icons/spectate.png","chars":["¯âÅ"],"ascent":-25,"height":48},{"type":"bitmap","file":"mcc:_fonts/health_bar/black_border/0_0.png","chars":["¯âÉ"],"ascent":-66,"height":7},{"type":"bitmap","file":"mcc:_fonts/health_bar/black_border/0_5.png","chars":["¯âæ"],"ascent":-66,"height":7},{"type":"bitmap","file":"mcc:_fonts/health_bar/black_border/1_0.png","chars":["¯âÆ"],"ascent":-66,"height":7},{"type":"bitmap","file":"mcc:_fonts/health_bar/black_border/1_5.png","chars":["¯âô"],"ascent":-66,"height":7},{"type":"bitmap","file":"mcc:_fonts/health_bar/black_border/2_0.png","chars":["¯âö"],"ascent":-66,"height":7},{"type":"bitmap","file":"mcc:_fonts/health_bar/black_border/disabled_0_5/0_0.png","chars":["¯âò"],"ascent":-66,"height":7},{"type":"bitmap","file":"mcc:_fonts/health_bar/black_border/disabled_0_5/0_5.png","chars":["¯âû"],"ascent":-66,"height":7},{"type":"bitmap","file":"mcc:_fonts/health_bar/black_border/disabled_0_5/1_0.png","chars":["¯âù"],"ascent":-66,"height":7},{"type":"bitmap","file":"mcc:_fonts/health_bar/black_border/disabled_0_5/1_5.png","chars":["¯âÿ"],"ascent":-66,"height":7},{"type":"bitmap","file":"mcc:_fonts/health_bar/black_border/disabled_1_0/0_0.png","chars":["¯âÖ"],"ascent":-66,"height":7},{"type":"bitmap","file":"mcc:_fonts/health_bar/black_border/disabled_1_0/0_5.png","chars":["¯âÜ"],"ascent":-66,"height":7},{"type":"bitmap","file":"mcc:_fonts/health_bar/black_border/disabled_1_0/1_0.png","chars":["¯âø"],"ascent":-66,"height":7},{"type":"bitmap","file":"mcc:_fonts/health_bar/black_border/disabled_1_5/0_0.png","chars":["¯â£"],"ascent":-66,"height":7},{"type":"bitmap","file":"mcc:_fonts/health_bar/black_border/disabled_1_5/0_5.png","chars":["¯âØ"],"ascent":-66,"height":7},{"type":"bitmap","file":"mcc:_fonts/health_bar/black_border/disabled_2_0/0_0.png","chars":["¯â×"],"ascent":-66,"height":7},{"type":"bitmap","file":"mcc:_fonts/health_bar/black_border/end_number/0-0.png","chars":["¯âƒ"],"ascent":-66,"height":7},{"type":"bitmap","file":"mcc:_fonts/health_bar/black_border/end_number/0-5.png","chars":["¯âá"],"ascent":-66,"height":7},{"type":"bitmap","file":"mcc:_fonts/health_bar/black_border/end_number/1-0.png","chars":["¯âí"],"ascent":-66,"height":7},{"type":"bitmap","file":"mcc:_fonts/health_bar/black_border/end_number/1-5.png","chars":["¯âó"],"ascent":-66,"height":7},{"type":"bitmap","file":"mcc:_fonts/health_bar/black_border/end_number/2-0.png","chars":["¯âú"],"ascent":-66,"height":7},{"type":"bitmap","file":"mcc:_fonts/health_bar/black_border/end_number/2-5.png","chars":["¯âñ"],"ascent":-66,"height":7},{"type":"bitmap","file":"mcc:_fonts/health_bar/black_border/end_number/3-0.png","chars":["¯âÑ"],"ascent":-66,"height":7},{"type":"bitmap","file":"mcc:_fonts/health_bar/black_border/end_number/3-5.png","chars":["¯âª"],"ascent":-66,"height":7},{"type":"bitmap","file":"mcc:_fonts/health_bar/black_border/end_number/4-0.png","chars":["¯âº"],"ascent":-66,"height":7},{"type":"bitmap","file":"mcc:_fonts/health_bar/black_border/end_number/4-5.png","chars":["¯â¿"],"ascent":-66,"height":7},{"type":"bitmap","file":"mcc:_fonts/health_bar/black_border/end_number/5-0.png","chars":["¯â®"],"ascent":-66,"height":7},{"type":"bitmap","file":"mcc:_fonts/health_bar/black_border/end_number/5-5.png","chars":["¯â¬"],"ascent":-66,"height":7},{"type":"bitmap","file":"mcc:_fonts/health_bar/black_border/end_number/6-0.png","chars":["¯â½"],"ascent":-66,"height":7},{"type":"bitmap","file":"mcc:_fonts/health_bar/black_border/end_number/6-5.png","chars":["¯â¼"],"ascent":-66,"height":7},{"type":"bitmap","file":"mcc:_fonts/health_bar/black_border/end_number/7-0.png","chars":["¯â¡"],"ascent":-66,"height":7},{"type":"bitmap","file":"mcc:_fonts/health_bar/black_border/end_number/7-5.png","chars":["¯â«"],"ascent":-66,"height":7},{"type":"bitmap","file":"mcc:_fonts/health_bar/black_border/end_number/8-0.png","chars":["¯â»"],"ascent":-66,"height":7},{"type":"bitmap","file":"mcc:_fonts/health_bar/blast_shield.png","chars":["¯â░"],"ascent":-66,"height":7},{"type":"bitmap","file":"mcc:_fonts/home.png","chars":["¯â▒"],"ascent":-66,"height":8},{"type":"bitmap","file":"mcc:_fonts/infinibag.png","chars":["¯â▓"],"ascent":-66,"height":8},{"type":"bitmap","file":"mcc:_fonts/info_blue.png","chars":["¯â│"],"ascent":-66,"height":8},{"type":"bitmap","file":"mcc:_fonts/kills.png","chars":["¯â┤"],"ascent":-66,"height":8},{"type":"bitmap","file":"mcc:_fonts/knick_knax_ticket.png","chars":["¯âÁ"],"ascent":-66,"height":8},{"type":"bitmap","file":"mcc:_fonts/loot_machine.png","chars":["¯âÂ"],"ascent":-66,"height":8},{"type":"bitmap","file":"mcc:_fonts/mastery_gate.png","chars":["¯âÀ"],"ascent":-66,"height":16},{"type":"bitmap","file":"mcc:_fonts/material_dust.png","chars":["¯â©"],"ascent":-66,"height":8},{"type":"bitmap","file":"mcc:_fonts/medals.png","chars":["¯â╣"],"ascent":-66,"height":8},{"type":"bitmap","file":"mcc:_fonts/mod_shield.png","chars":["¯â║"],"ascent":-66,"height":8},{"type":"bitmap","file":"mcc:_fonts/navigator_small.png","chars":["¯â╗"],"ascent":-66,"height":8},{"type":"bitmap","file":"mcc:_fonts/noxcrew.png","chars":["¯â╝"],"ascent":-66,"height":8},{"type":"bitmap","file":"mcc:_fonts/npcs/barber.png","chars":["¯â¢"],"ascent":-66,"height":8},{"type":"bitmap","file":"mcc:_fonts/npcs/faction_master.png","chars":["¯â¥"],"ascent":-66,"height":8},{"type":"bitmap","file":"mcc:_fonts/npcs/marker_bank.png","chars":["¯â┐"],"ascent":-43,"height":31},{"type":"bitmap","file":"mcc:_fonts/npcs/marker_barber.png","chars":["¯äÇ"],"ascent":-43,"height":31},{"type":"bitmap","file":"mcc:_fonts/npcs/marker_battle_pass.png","chars":["¯äü"],"ascent":-43,"height":31},{"type":"bitmap","file":"mcc:_fonts/npcs/marker_blueprint_assembly.png","chars":["¯äé"],"ascent":-43,"height":31},{"type":"bitmap","file":"mcc:_fonts/npcs/marker_candy.png","chars":["¯äâ"],"ascent":-43,"height":31},{"type":"bitmap","file":"mcc:_fonts/npcs/marker_crafting.png","chars":["¯ää"],"ascent":-43,"height":31},{"type":"bitmap","file":"mcc:_fonts/npcs/marker_crate_machine.png","chars":["¯äà"],"ascent":-43,"height":31},{"type":"bitmap","file":"mcc:_fonts/npcs/marker_drinks.png","chars":["¯äå"],"ascent":-43,"height":31},{"type":"bitmap","file":"mcc:_fonts/npcs/marker_faction_master.png","chars":["¯äç"],"ascent":-43,"height":31},{"type":"bitmap","file":"mcc:_fonts/npcs/marker_food.png","chars":["¯äê"],"ascent":-43,"height":31},{"type":"bitmap","file":"mcc:_fonts/npcs/marker_fusion_crafting.png","chars":["¯äë"],"ascent":-43,"height":31},{"type":"bitmap","file":"mcc:_fonts/npcs/marker_gadget.png","chars":["¯äè"],"ascent":-43,"height":31},{"type":"bitmap","file":"mcc:_fonts/npcs/marker_game_mastery.png","chars":["¯äï"],"ascent":-43,"height":31},{"type":"bitmap","file":"mcc:_fonts/npcs/marker_newspaper.png","chars":["¯äî"],"ascent":-43,"height":31},{"type":"bitmap","file":"mcc:_fonts/npcs/marker_quest.png","chars":["¯äì"],"ascent":-43,"height":31},{"type":"bitmap","file":"mcc:_fonts/npcs/marker_quest_framed.png","chars":["¯äÄ"],"ascent":-43,"height":31},{"type":"bitmap","file":"mcc:_fonts/npcs/marker_scavenging.png","chars":["¯äÅ"],"ascent":-43,"height":31},{"type":"bitmap","file":"mcc:_fonts/npcs/marker_summer_machine.png","chars":["¯äÉ"],"ascent":-43,"height":31},{"type":"bitmap","file":"mcc:_fonts/npcs/marker_summer_quest.png","chars":["¯äæ"],"ascent":-43,"height":31},{"type":"bitmap","file":"mcc:_fonts/npcs/marker_vendor.png","chars":["¯äÆ"],"ascent":-43,"height":31},{"type":"bitmap","file":"mcc:_fonts/npcs/marker_wardrobe.png","chars":["¯äô"],"ascent":-43,"height":31},{"type":"bitmap","file":"mcc:_fonts/npcs/questgiver.png","chars":["¯äö"],"ascent":-66,"height":8},{"type":"bitmap","file":"mcc:_fonts/npcs/shop.png","chars":["¯äò"],"ascent":-66,"height":8},{"type":"bitmap","file":"mcc:_fonts/npcs/shop_bank.png","chars":["¯äû"],"ascent":-66,"height":16},{"type":"bitmap","file":"mcc:_fonts/npcs/shop_burger.png","chars":["¯äù"],"ascent":-66,"height":16},{"type":"bitmap","file":"mcc:_fonts/npcs/shop_clothing.png","chars":["¯äÿ"],"ascent":-66,"height":16},{"type":"bitmap","file":"mcc:_fonts/npcs/shop_gadget.png","chars":["¯äÖ"],"ascent":-66,"height":16},{"type":"bitmap","file":"mcc:_fonts/npcs/shop_tea.png","chars":["¯äÜ"],"ascent":-66,"height":16},{"type":"bitmap","file":"mcc:_fonts/offline.png","chars":["¯äø"],"ascent":-66,"height":8},{"type":"bitmap","file":"mcc:_fonts/open_link.png","chars":["¯ä£"],"ascent":-66,"height":8},{"type":"bitmap","file":"mcc:_fonts/parkour_warrior/completion_advanced.png","chars":["¯äØ"],"ascent":-66,"height":16},{"type":"bitmap","file":"mcc:_fonts/parkour_warrior/completion_advanced_empty.png","chars":["¯ä×"],"ascent":-66,"height":16},{"type":"bitmap","file":"mcc:_fonts/parkour_warrior/completion_advanced_small.png","chars":["¯äƒ"],"ascent":-66,"height":8},{"type":"bitmap","file":"mcc:_fonts/parkour_warrior/completion_standard.png","chars":["¯äá"],"ascent":-66,"height":16},{"type":"bitmap","file":"mcc:_fonts/parkour_warrior/completion_standard_empty.png","chars":["¯äí"],"ascent":-66,"height":16},{"type":"bitmap","file":"mcc:_fonts/parkour_warrior/completion_standard_small.png","chars":["¯äó"],"ascent":-66,"height":8},{"type":"bitmap","file":"mcc:_fonts/parkour_warrior/completion_total.png","chars":["¯äú"],"ascent":-66,"height":16},{"type":"bitmap","file":"mcc:_fonts/parkour_warrior/completion_total_empty.png","chars":["¯äñ"],"ascent":-66,"height":16},{"type":"bitmap","file":"mcc:_fonts/parkour_warrior/completion_total_small.png","chars":["¯äÑ"],"ascent":-66,"height":8},{"type":"bitmap","file":"mcc:_fonts/parkour_warrior/frog_bronze.png","chars":["¯äª"],"ascent":-66,"height":8},{"type":"bitmap","file":"mcc:_fonts/parkour_warrior/frog_empty.png","chars":["¯äº"],"ascent":-66,"height":8},{"type":"bitmap","file":"mcc:_fonts/parkour_warrior/frog_gold.png","chars":["¯ä¿"],"ascent":-66,"height":8},{"type":"bitmap","file":"mcc:_fonts/parkour_warrior/frog_silver.png","chars":["¯ä®"],"ascent":-66,"height":8},{"type":"bitmap","file":"mcc:_fonts/parkour_warrior/medal.png","chars":["¯ä¬"],"ascent":-66,"height":8},{"type":"bitmap","file":"mcc:_fonts/parkour_warrior/medal_bronze.png","chars":["¯ä½"],"ascent":-66,"height":8},{"type":"bitmap","file":"mcc:_fonts/parkour_warrior/medal_gold.png","chars":["¯ä¼"],"ascent":-66,"height":8},{"type":"bitmap","file":"mcc:_fonts/parkour_warrior/medal_silver.png","chars":["¯ä¡"],"ascent":-66,"height":8},{"type":"bitmap","file":"mcc:_fonts/parkour_warrior/medal_stone.png","chars":["¯ä«"],"ascent":-66,"height":8},{"type":"bitmap","file":"mcc:_fonts/parkour_warrior/point_bonus_1.png","chars":["¯ä»"],"ascent":-66,"height":14},{"type":"bitmap","file":"mcc:_fonts/parkour_warrior/point_bonus_2.png","chars":["¯ä░"],"ascent":-66,"height":14},{"type":"bitmap","file":"mcc:_fonts/parkour_warrior/point_bonus_3.png","chars":["¯ä▒"],"ascent":-66,"height":14},{"type":"bitmap","file":"mcc:_fonts/parkour_warrior/point_empty.png","chars":["¯ä▓"],"ascent":-66,"height":8},{"type":"bitmap","file":"mcc:_fonts/parkour_warrior/point_empty_bonus.png","chars":["¯ä│"],"ascent":-66,"height":14},{"type":"bitmap","file":"mcc:_fonts/parkour_warrior/point_full.png","chars":["¯ä┤"],"ascent":-66,"height":8},{"type":"bitmap","file":"mcc:_fonts/party_leader.png","chars":["¯äÁ"],"ascent":-66,"height":8},{"type":"bitmap","file":"mcc:_fonts/player.png","chars":["¯äÂ"],"ascent":-66,"height":8},{"type":"bitmap","file":"mcc:_fonts/plus_small.png","chars":["¯äÀ"],"ascent":-66,"height":8},{"type":"bitmap","file":"mcc:_fonts/progress_counter/blank.png","chars":["¯ä©"],"ascent":-66,"height":7},{"type":"bitmap","file":"mcc:_fonts/progress_counter/blue/full.png","chars":["¯ä╣"],"ascent":-66,"height":7},{"type":"bitmap","file":"mcc:_fonts/progress_counter/blue/half.png","chars":["¯ä║"],"ascent":-66,"height":7},{"type":"bitmap","file":"mcc:_fonts/progress_counter/blue_square/full.png","chars":["¯ä╗"],"ascent":-66,"height":7},{"type":"bitmap","file":"mcc:_fonts/progress_counter/empty.png","chars":["¯ä╝"],"ascent":-66,"height":7},{"type":"bitmap","file":"mcc:_fonts/progress_counter/full.png","chars":["¯ä¢"],"ascent":-66,"height":7},{"type":"bitmap","file":"mcc:_fonts/progress_counter/half.png","chars":["¯ä¥"],"ascent":-66,"height":7},{"type":"bitmap","file":"mcc:_fonts/progress_counter/orange/full.png","chars":["¯ä┐"],"ascent":-66,"height":7},{"type":"bitmap","file":"mcc:_fonts/progress_counter/orange/half.png","chars":["¯àÇ"],"ascent":-66,"height":7},{"type":"bitmap","file":"mcc:_fonts/progress_counter/orange_square/full.png","chars":["¯àü"],"ascent":-66,"height":7},{"type":"bitmap","file":"mcc:_fonts/progress_counter/red/full.png","chars":["¯àé"],"ascent":-66,"height":7},{"type":"bitmap","file":"mcc:_fonts/progress_counter/red/half.png","chars":["¯àâ"],"ascent":-66,"height":7},{"type":"bitmap","file":"mcc:_fonts/quest_log.png","chars":["¯àä"],"ascent":-66,"height":8},{"type":"bitmap","file":"mcc:_fonts/ranks_long/admin.png","chars":["¯àà"],"ascent":-66,"height":7},{"type":"bitmap","file":"mcc:_fonts/ranks_long/contestant.png","chars":["¯àå"],"ascent":-66,"height":9},{"type":"bitmap","file":"mcc:_fonts/ranks_long/creator.png","chars":["¯àç"],"ascent":-66,"height":9},{"type":"bitmap","file":"mcc:_fonts/ranks_long/mod.png","chars":["¯àê"],"ascent":-66,"height":9},{"type":"bitmap","file":"mcc:_fonts/ranks_long/noxcrew.png","chars":["¯àë"],"ascent":-66,"height":9},{"type":"bitmap","file":"mcc:_fonts/ranks_long/plus.png","chars":["¯àè"],"ascent":-66,"height":9},{"type":"bitmap","file":"mcc:_fonts/ranks_long/rank_1.png","chars":["¯àï"],"ascent":-66,"height":9},{"type":"bitmap","file":"mcc:_fonts/ranks_long/rank_2.png","chars":["¯àî"],"ascent":-66,"height":9},{"type":"bitmap","file":"mcc:_fonts/ranks_long/rank_3.png","chars":["¯àì"],"ascent":-66,"height":9},{"type":"bitmap","file":"mcc:_fonts/ranks_long/vip.png","chars":["¯àÄ"],"ascent":-66,"height":9},{"type":"bitmap","file":"mcc:_fonts/ranks_short/admin.png","chars":["¯àÅ"],"ascent":-66,"height":8},{"type":"bitmap","file":"mcc:_fonts/ranks_short/basic.png","chars":["¯àÉ"],"ascent":-66,"height":8},{"type":"bitmap","file":"mcc:_fonts/ranks_short/contestant.png","chars":["¯àæ"],"ascent":-66,"height":8},{"type":"bitmap","file":"mcc:_fonts/ranks_short/mod.png","chars":["¯àÆ"],"ascent":-66,"height":8},{"type":"bitmap","file":"mcc:_fonts/ranks_short/noxcrew.png","chars":["¯àô"],"ascent":-66,"height":8},{"type":"bitmap","file":"mcc:_fonts/ranks_short/plus_1.png","chars":["¯àö"],"ascent":-66,"height":8},{"type":"bitmap","file":"mcc:_fonts/ranks_short/plus_1_simple.png","chars":["¯àò"],"ascent":-66,"height":8},{"type":"bitmap","file":"mcc:_fonts/ranks_short/plus_2.png","chars":["¯àû"],"ascent":-66,"height":8},{"type":"bitmap","file":"mcc:_fonts/ranks_short/plus_2_simple.png","chars":["¯àù"],"ascent":-66,"height":8},{"type":"bitmap","file":"mcc:_fonts/ranks_short/plus_3.png","chars":["¯àÿ"],"ascent":-66,"height":8},{"type":"bitmap","file":"mcc:_fonts/ranks_short/plus_3_simple.png","chars":["¯àÖ"],"ascent":-66,"height":8},{"type":"bitmap","file":"mcc:_fonts/ranks_short/rank_1.png","chars":["¯àÜ"],"ascent":-66,"height":8},{"type":"bitmap","file":"mcc:_fonts/ranks_short/rank_2.png","chars":["¯àø"],"ascent":-66,"height":8},{"type":"bitmap","file":"mcc:_fonts/ranks_short/rank_3.png","chars":["¯à£"],"ascent":-66,"height":8},{"type":"bitmap","file":"mcc:_fonts/ranks_short/vip.png","chars":["¯àØ"],"ascent":-66,"height":8},{"type":"bitmap","file":"mcc:_fonts/remix/large.png","chars":["¯à×"],"ascent":-66,"height":18},{"type":"bitmap","file":"mcc:_fonts/remix/small.png","chars":["¯àƒ"],"ascent":-66,"height":9},{"type":"bitmap","file":"mcc:_fonts/rocket.png","chars":["¯àá"],"ascent":-66,"height":8},{"type":"bitmap","file":"mcc:_fonts/royal_reputation.png","chars":["¯àí"],"ascent":-66,"height":8},{"type":"bitmap","file":"mcc:_fonts/scavenging.png","chars":["¯àó"],"ascent":-66,"height":8},{"type":"bitmap","file":"mcc:_fonts/score_point.png","chars":["¯àú"],"ascent":-66,"height":8},{"type":"bitmap","file":"mcc:_fonts/select.png","chars":["¯àñ"],"ascent":-67,"height":11},{"type":"bitmap","file":"mcc:_fonts/silver.png","chars":["¯àÑ"],"ascent":-66,"height":8},{"type":"bitmap","file":"mcc:_fonts/skull.png","chars":["¯àª"],"ascent":-66,"height":8},{"type":"bitmap","file":"mcc:_fonts/skull_small.png","chars":["¯àº"],"ascent":-66,"height":8},{"type":"bitmap","file":"mcc:_fonts/sot_exit.png","chars":["¯à¿"],"ascent":-66,"height":8},{"type":"bitmap","file":"mcc:_fonts/sot_tomb.png","chars":["¯à®"],"ascent":-66,"height":8},{"type":"bitmap","file":"mcc:_fonts/split_down.png","chars":["¯à¬"],"ascent":-66,"height":8},{"type":"bitmap","file":"mcc:_fonts/split_up.png","chars":["¯à½"],"ascent":-66,"height":8},{"type":"bitmap","file":"mcc:_fonts/star.png","chars":["¯à¼"],"ascent":-66,"height":8},{"type":"bitmap","file":"mcc:_fonts/start.png","chars":["¯à¡"],"ascent":-66,"height":8},{"type":"bitmap","file":"mcc:_fonts/steve.png","chars":["¯à«"],"ascent":-66,"height":8},{"type":"bitmap","file":"mcc:_fonts/summer_event_small.png","chars":["¯à»"],"ascent":-66,"height":8},{"type":"bitmap","file":"mcc:_fonts/summer_key_small.png","chars":["¯à░"],"ascent":-66,"height":8},{"type":"bitmap","file":"mcc:_fonts/summer_seashell_small.png","chars":["¯à▒"],"ascent":-66,"height":8},{"type":"bitmap","file":"mcc:_fonts/summer_token_small.png","chars":["¯à▓"],"ascent":-66,"height":8},{"type":"bitmap","file":"mcc:_fonts/sweets.png","chars":["¯à│"],"ascent":-66,"height":8},{"type":"bitmap","file":"mcc:_fonts/tab_logo.png","chars":["¯à┤"],"ascent":-63,"height":128},{"type":"bitmap","file":"mcc:_fonts/tagger.png","chars":["¯àÁ"],"ascent":-66,"height":8},{"type":"bitmap","file":"mcc:_fonts/team/aqua.png","chars":["¯àÂ"],"ascent":-66,"height":8},{"type":"bitmap","file":"mcc:_fonts/team/aqua_bar.png","chars":["¯àÀ"],"ascent":-63,"height":16},{"type":"bitmap","file":"mcc:_fonts/team/aqua_big.png","chars":["¯à©"],"ascent":-66,"height":16},{"type":"bitmap","file":"mcc:_fonts/team/aqua_glow.png","chars":["¯à╣"],"ascent":-66,"height":16},{"type":"bitmap","file":"mcc:_fonts/team/aqua_glow_small.png","chars":["¯à║"],"ascent":-66,"height":8},{"type":"bitmap","file":"mcc:_fonts/team/aqua_gray.png","chars":["¯à╗"],"ascent":-66,"height":8},{"type":"bitmap","file":"mcc:_fonts/team/aqua_moment.png","chars":["¯à╝"],"ascent":-65,"height":8},{"type":"bitmap","file":"mcc:_fonts/team/aqua_spec.png","chars":["¯à¢"],"ascent":-63,"height":16},{"type":"bitmap","file":"mcc:_fonts/team/aqua_spec_gray.png","chars":["¯à¥"],"ascent":-63,"height":16},{"type":"bitmap","file":"mcc:_fonts/team/blue.png","chars":["¯à┐"],"ascent":-66,"height":8},{"type":"bitmap","file":"mcc:_fonts/team/blue_bar.png","chars":["¯åÇ"],"ascent":-63,"height":16},{"type":"bitmap","file":"mcc:_fonts/team/blue_big.png","chars":["¯åü"],"ascent":-66,"height":16},{"type":"bitmap","file":"mcc:_fonts/team/blue_glow.png","chars":["¯åé"],"ascent":-66,"height":16},{"type":"bitmap","file":"mcc:_fonts/team/blue_glow_small.png","chars":["¯åâ"],"ascent":-66,"height":8},{"type":"bitmap","file":"mcc:_fonts/team/blue_gray.png","chars":["¯åä"],"ascent":-66,"height":8},{"type":"bitmap","file":"mcc:_fonts/team/blue_moment.png","chars":["¯åà"],"ascent":-65,"height":8},{"type":"bitmap","file":"mcc:_fonts/team/blue_spec.png","chars":["¯åå"],"ascent":-63,"height":16},{"type":"bitmap","file":"mcc:_fonts/team/blue_spec_gray.png","chars":["¯åç"],"ascent":-63,"height":16},{"type":"bitmap","file":"mcc:_fonts/team/cyan.png","chars":["¯åê"],"ascent":-66,"height":8},{"type":"bitmap","file":"mcc:_fonts/team/cyan_bar.png","chars":["¯åë"],"ascent":-63,"height":16},{"type":"bitmap","file":"mcc:_fonts/team/cyan_big.png","chars":["¯åè"],"ascent":-66,"height":16},{"type":"bitmap","file":"mcc:_fonts/team/cyan_glow.png","chars":["¯åï"],"ascent":-66,"height":16},{"type":"bitmap","file":"mcc:_fonts/team/cyan_glow_small.png","chars":["¯åî"],"ascent":-66,"height":8},{"type":"bitmap","file":"mcc:_fonts/team/cyan_gray.png","chars":["¯åì"],"ascent":-66,"height":8},{"type":"bitmap","file":"mcc:_fonts/team/cyan_moment.png","chars":["¯åÄ"],"ascent":-65,"height":8},{"type":"bitmap","file":"mcc:_fonts/team/cyan_spec.png","chars":["¯åÅ"],"ascent":-63,"height":16},{"type":"bitmap","file":"mcc:_fonts/team/cyan_spec_gray.png","chars":["¯åÉ"],"ascent":-63,"height":16},{"type":"bitmap","file":"mcc:_fonts/team/green.png","chars":["¯åæ"],"ascent":-66,"height":8},{"type":"bitmap","file":"mcc:_fonts/team/green_bar.png","chars":["¯åÆ"],"ascent":-63,"height":16},{"type":"bitmap","file":"mcc:_fonts/team/green_big.png","chars":["¯åô"],"ascent":-66,"height":16},{"type":"bitmap","file":"mcc:_fonts/team/green_glow.png","chars":["¯åö"],"ascent":-66,"height":16},{"type":"bitmap","file":"mcc:_fonts/team/green_glow_small.png","chars":["¯åò"],"ascent":-66,"height":8},{"type":"bitmap","file":"mcc:_fonts/team/green_gray.png","chars":["¯åû"],"ascent":-66,"height":8},{"type":"bitmap","file":"mcc:_fonts/team/green_moment.png","chars":["¯åù"],"ascent":-65,"height":8},{"type":"bitmap","file":"mcc:_fonts/team/green_spec.png","chars":["¯åÿ"],"ascent":-63,"height":16},{"type":"bitmap","file":"mcc:_fonts/team/green_spec_gray.png","chars":["¯åÖ"],"ascent":-63,"height":16},{"type":"bitmap","file":"mcc:_fonts/team/lime.png","chars":["¯åÜ"],"ascent":-66,"height":8},{"type":"bitmap","file":"mcc:_fonts/team/lime_bar.png","chars":["¯åø"],"ascent":-63,"height":16},{"type":"bitmap","file":"mcc:_fonts/team/lime_big.png","chars":["¯å£"],"ascent":-66,"height":16},{"type":"bitmap","file":"mcc:_fonts/team/lime_glow.png","chars":["¯åØ"],"ascent":-66,"height":16},{"type":"bitmap","file":"mcc:_fonts/team/lime_glow_small.png","chars":["¯å×"],"ascent":-66,"height":8},{"type":"bitmap","file":"mcc:_fonts/team/lime_gray.png","chars":["¯åƒ"],"ascent":-66,"height":8},{"type":"bitmap","file":"mcc:_fonts/team/lime_moment.png","chars":["¯åá"],"ascent":-65,"height":8},{"type":"bitmap","file":"mcc:_fonts/team/lime_spec.png","chars":["¯åí"],"ascent":-63,"height":16},{"type":"bitmap","file":"mcc:_fonts/team/lime_spec_gray.png","chars":["¯åó"],"ascent":-63,"height":16},{"type":"bitmap","file":"mcc:_fonts/team/orange.png","chars":["¯åú"],"ascent":-66,"height":8},{"type":"bitmap","file":"mcc:_fonts/team/orange_bar.png","chars":["¯åñ"],"ascent":-63,"height":16},{"type":"bitmap","file":"mcc:_fonts/team/orange_big.png","chars":["¯åÑ"],"ascent":-66,"height":16},{"type":"bitmap","file":"mcc:_fonts/team/orange_glow.png","chars":["¯åª"],"ascent":-66,"height":16},{"type":"bitmap","file":"mcc:_fonts/team/orange_glow_small.png","chars":["¯åº"],"ascent":-66,"height":8},{"type":"bitmap","file":"mcc:_fonts/team/orange_gray.png","chars":["¯å¿"],"ascent":-66,"height":8},{"type":"bitmap","file":"mcc:_fonts/team/orange_moment.png","chars":["¯å®"],"ascent":-65,"height":8},{"type":"bitmap","file":"mcc:_fonts/team/orange_spec.png","chars":["¯å¬"],"ascent":-63,"height":16},{"type":"bitmap","file":"mcc:_fonts/team/orange_spec_gray.png","chars":["¯å½"],"ascent":-63,"height":16},{"type":"bitmap","file":"mcc:_fonts/team/pink.png","chars":["¯å¼"],"ascent":-66,"height":8},{"type":"bitmap","file":"mcc:_fonts/team/pink_bar.png","chars":["¯å¡"],"ascent":-63,"height":16},{"type":"bitmap","file":"mcc:_fonts/team/pink_big.png","chars":["¯å«"],"ascent":-66,"height":16},{"type":"bitmap","file":"mcc:_fonts/team/pink_glow.png","chars":["¯å»"],"ascent":-66,"height":16},{"type":"bitmap","file":"mcc:_fonts/team/pink_glow_small.png","chars":["¯å░"],"ascent":-66,"height":8},{"type":"bitmap","file":"mcc:_fonts/team/pink_gray.png","chars":["¯å▒"],"ascent":-66,"height":8},{"type":"bitmap","file":"mcc:_fonts/team/pink_moment.png","chars":["¯å▓"],"ascent":-65,"height":8},{"type":"bitmap","file":"mcc:_fonts/team/pink_spec.png","chars":["¯å│"],"ascent":-63,"height":16},{"type":"bitmap","file":"mcc:_fonts/team/pink_spec_gray.png","chars":["¯å┤"],"ascent":-63,"height":16},{"type":"bitmap","file":"mcc:_fonts/team/purple.png","chars":["¯åÁ"],"ascent":-66,"height":8},{"type":"bitmap","file":"mcc:_fonts/team/purple_bar.png","chars":["¯åÂ"],"ascent":-63,"height":16},{"type":"bitmap","file":"mcc:_fonts/team/purple_big.png","chars":["¯åÀ"],"ascent":-66,"height":16},{"type":"bitmap","file":"mcc:_fonts/team/purple_glow.png","chars":["¯å©"],"ascent":-66,"height":16},{"type":"bitmap","file":"mcc:_fonts/team/purple_glow_small.png","chars":["¯å╣"],"ascent":-66,"height":8},{"type":"bitmap","file":"mcc:_fonts/team/purple_gray.png","chars":["¯å║"],"ascent":-66,"height":8},{"type":"bitmap","file":"mcc:_fonts/team/purple_moment.png","chars":["¯å╗"],"ascent":-65,"height":8},{"type":"bitmap","file":"mcc:_fonts/team/purple_spec.png","chars":["¯å╝"],"ascent":-63,"height":16},{"type":"bitmap","file":"mcc:_fonts/team/purple_spec_gray.png","chars":["¯å¢"],"ascent":-63,"height":16},{"type":"bitmap","file":"mcc:_fonts/team/red.png","chars":["¯å¥"],"ascent":-66,"height":8},{"type":"bitmap","file":"mcc:_fonts/team/red_bar.png","chars":["¯å┐"],"ascent":-63,"height":16},{"type":"bitmap","file":"mcc:_fonts/team/red_big.png","chars":["¯çÇ"],"ascent":-66,"height":16},{"type":"bitmap","file":"mcc:_fonts/team/red_glow.png","chars":["¯çü"],"ascent":-66,"height":16},{"type":"bitmap","file":"mcc:_fonts/team/red_glow_small.png","chars":["¯çé"],"ascent":-66,"height":8},{"type":"bitmap","file":"mcc:_fonts/team/red_gray.png","chars":["¯çâ"],"ascent":-66,"height":8},{"type":"bitmap","file":"mcc:_fonts/team/red_moment.png","chars":["¯çä"],"ascent":-65,"height":8},{"type":"bitmap","file":"mcc:_fonts/team/red_spec.png","chars":["¯çà"],"ascent":-63,"height":16},{"type":"bitmap","file":"mcc:_fonts/team/red_spec_gray.png","chars":["¯çå"],"ascent":-63,"height":16},{"type":"bitmap","file":"mcc:_fonts/team/spectator.png","chars":["¯çç"],"ascent":-66,"height":8},{"type":"bitmap","file":"mcc:_fonts/team/spectators.png","chars":["¯çê"],"ascent":-66,"height":8},{"type":"bitmap","file":"mcc:_fonts/team/yellow.png","chars":["¯çë"],"ascent":-66,"height":8},{"type":"bitmap","file":"mcc:_fonts/team/yellow_bar.png","chars":["¯çè"],"ascent":-63,"height":16},{"type":"bitmap","file":"mcc:_fonts/team/yellow_big.png","chars":["¯çï"],"ascent":-66,"height":16},{"type":"bitmap","file":"mcc:_fonts/team/yellow_glow.png","chars":["¯çî"],"ascent":-66,"height":16},{"type":"bitmap","file":"mcc:_fonts/team/yellow_glow_small.png","chars":["¯çì"],"ascent":-66,"height":8},{"type":"bitmap","file":"mcc:_fonts/team/yellow_gray.png","chars":["¯çÄ"],"ascent":-66,"height":8},{"type":"bitmap","file":"mcc:_fonts/team/yellow_moment.png","chars":["¯çÅ"],"ascent":-65,"height":8},{"type":"bitmap","file":"mcc:_fonts/team/yellow_spec.png","chars":["¯çÉ"],"ascent":-63,"height":16},{"type":"bitmap","file":"mcc:_fonts/team/yellow_spec_gray.png","chars":["¯çæ"],"ascent":-63,"height":16},{"type":"bitmap","file":"mcc:_fonts/team_flag.png","chars":["¯çÆ"],"ascent":-66,"height":8},{"type":"bitmap","file":"mcc:_fonts/team_flag/aqua.png","chars":["¯çô"],"ascent":-66,"height":8},{"type":"bitmap","file":"mcc:_fonts/team_flag/aqua_bar.png","chars":["¯çö"],"ascent":-63,"height":16},{"type":"bitmap","file":"mcc:_fonts/team_flag/aqua_big.png","chars":["¯çò"],"ascent":-66,"height":16},{"type":"bitmap","file":"mcc:_fonts/team_flag/aqua_moment.png","chars":["¯çû"],"ascent":-65,"height":8},{"type":"bitmap","file":"mcc:_fonts/team_flag/blue.png","chars":["¯çù"],"ascent":-66,"height":8},{"type":"bitmap","file":"mcc:_fonts/team_flag/blue_bar.png","chars":["¯çÿ"],"ascent":-63,"height":16},{"type":"bitmap","file":"mcc:_fonts/team_flag/blue_big.png","chars":["¯çÖ"],"ascent":-66,"height":16},{"type":"bitmap","file":"mcc:_fonts/team_flag/blue_moment.png","chars":["¯çÜ"],"ascent":-65,"height":8},{"type":"bitmap","file":"mcc:_fonts/team_flag/cyan.png","chars":["¯çø"],"ascent":-66,"height":8},{"type":"bitmap","file":"mcc:_fonts/team_flag/cyan_bar.png","chars":["¯ç£"],"ascent":-63,"height":16},{"type":"bitmap","file":"mcc:_fonts/team_flag/cyan_big.png","chars":["¯çØ"],"ascent":-66,"height":16},{"type":"bitmap","file":"mcc:_fonts/team_flag/cyan_moment.png","chars":["¯ç×"],"ascent":-65,"height":8},{"type":"bitmap","file":"mcc:_fonts/team_flag/green.png","chars":["¯çƒ"],"ascent":-66,"height":8},{"type":"bitmap","file":"mcc:_fonts/team_flag/green_bar.png","chars":["¯çá"],"ascent":-63,"height":16},{"type":"bitmap","file":"mcc:_fonts/team_flag/green_big.png","chars":["¯çí"],"ascent":-66,"height":16},{"type":"bitmap","file":"mcc:_fonts/team_flag/green_moment.png","chars":["¯çó"],"ascent":-65,"height":8},{"type":"bitmap","file":"mcc:_fonts/team_flag/lime.png","chars":["¯çú"],"ascent":-66,"height":8},{"type":"bitmap","file":"mcc:_fonts/team_flag/lime_bar.png","chars":["¯çñ"],"ascent":-63,"height":16},{"type":"bitmap","file":"mcc:_fonts/team_flag/lime_big.png","chars":["¯çÑ"],"ascent":-66,"height":16},{"type":"bitmap","file":"mcc:_fonts/team_flag/lime_moment.png","chars":["¯çª"],"ascent":-65,"height":8},{"type":"bitmap","file":"mcc:_fonts/team_flag/orange.png","chars":["¯çº"],"ascent":-66,"height":8},{"type":"bitmap","file":"mcc:_fonts/team_flag/orange_bar.png","chars":["¯ç¿"],"ascent":-63,"height":16},{"type":"bitmap","file":"mcc:_fonts/team_flag/orange_big.png","chars":["¯ç®"],"ascent":-66,"height":16},{"type":"bitmap","file":"mcc:_fonts/team_flag/orange_moment.png","chars":["¯ç¬"],"ascent":-65,"height":8},{"type":"bitmap","file":"mcc:_fonts/team_flag/pink.png","chars":["¯ç½"],"ascent":-66,"height":8},{"type":"bitmap","file":"mcc:_fonts/team_flag/pink_bar.png","chars":["¯ç¼"],"ascent":-63,"height":16},{"type":"bitmap","file":"mcc:_fonts/team_flag/pink_big.png","chars":["¯ç¡"],"ascent":-66,"height":16},{"type":"bitmap","file":"mcc:_fonts/team_flag/pink_moment.png","chars":["¯ç«"],"ascent":-65,"height":8},{"type":"bitmap","file":"mcc:_fonts/team_flag/purple.png","chars":["¯ç»"],"ascent":-66,"height":8},{"type":"bitmap","file":"mcc:_fonts/team_flag/purple_bar.png","chars":["¯ç░"],"ascent":-63,"height":16},{"type":"bitmap","file":"mcc:_fonts/team_flag/purple_big.png","chars":["¯ç▒"],"ascent":-66,"height":16},{"type":"bitmap","file":"mcc:_fonts/team_flag/purple_moment.png","chars":["¯ç▓"],"ascent":-65,"height":8},{"type":"bitmap","file":"mcc:_fonts/team_flag/red.png","chars":["¯ç│"],"ascent":-66,"height":8},{"type":"bitmap","file":"mcc:_fonts/team_flag/red_bar.png","chars":["¯ç┤"],"ascent":-63,"height":16},{"type":"bitmap","file":"mcc:_fonts/team_flag/red_big.png","chars":["¯çÁ"],"ascent":-66,"height":16},{"type":"bitmap","file":"mcc:_fonts/team_flag/red_moment.png","chars":["¯çÂ"],"ascent":-65,"height":8},{"type":"bitmap","file":"mcc:_fonts/team_flag/yellow.png","chars":["¯çÀ"],"ascent":-66,"height":8},{"type":"bitmap","file":"mcc:_fonts/team_flag/yellow_bar.png","chars":["¯ç©"],"ascent":-63,"height":16},{"type":"bitmap","file":"mcc:_fonts/team_flag/yellow_big.png","chars":["¯ç╣"],"ascent":-66,"height":16},{"type":"bitmap","file":"mcc:_fonts/team_flag/yellow_moment.png","chars":["¯ç║"],"ascent":-65,"height":8},{"type":"bitmap","file":"mcc:_fonts/team_flag_big.png","chars":["¯ç╗"],"ascent":-63,"height":16},{"type":"bitmap","file":"mcc:_fonts/team_flag_v2.png","chars":["¯ç╝"],"ascent":-66,"height":8},{"type":"bitmap","file":"mcc:_fonts/team_halloween/aqua.png","chars":["¯ç¢"],"ascent":-66,"height":8},{"type":"bitmap","file":"mcc:_fonts/team_halloween/aqua_bar.png","chars":["¯ç¥"],"ascent":-63,"height":16},{"type":"bitmap","file":"mcc:_fonts/team_halloween/aqua_big.png","chars":["¯ç┐"],"ascent":-66,"height":16},{"type":"bitmap","file":"mcc:_fonts/team_halloween/aqua_glow.png","chars":["¯êÇ"],"ascent":-66,"height":16},{"type":"bitmap","file":"mcc:_fonts/team_halloween/aqua_moment.png","chars":["¯êü"],"ascent":-65,"height":8},{"type":"bitmap","file":"mcc:_fonts/team_halloween/aqua_spec.png","chars":["¯êé"],"ascent":-63,"height":16},{"type":"bitmap","file":"mcc:_fonts/team_halloween/aqua_spec_gray.png","chars":["¯êâ"],"ascent":-63,"height":16},{"type":"bitmap","file":"mcc:_fonts/team_halloween/blue.png","chars":["¯êä"],"ascent":-66,"height":8},{"type":"bitmap","file":"mcc:_fonts/team_halloween/blue_bar.png","chars":["¯êà"],"ascent":-63,"height":16},{"type":"bitmap","file":"mcc:_fonts/team_halloween/blue_big.png","chars":["¯êå"],"ascent":-66,"height":16},{"type":"bitmap","file":"mcc:_fonts/team_halloween/blue_glow.png","chars":["¯êç"],"ascent":-66,"height":16},{"type":"bitmap","file":"mcc:_fonts/team_halloween/blue_moment.png","chars":["¯êê"],"ascent":-65,"height":8},{"type":"bitmap","file":"mcc:_fonts/team_halloween/blue_spec.png","chars":["¯êë"],"ascent":-63,"height":16},{"type":"bitmap","file":"mcc:_fonts/team_halloween/blue_spec_gray.png","chars":["¯êè"],"ascent":-63,"height":16},{"type":"bitmap","file":"mcc:_fonts/team_halloween/cyan.png","chars":["¯êï"],"ascent":-66,"height":8},{"type":"bitmap","file":"mcc:_fonts/team_halloween/cyan_bar.png","chars":["¯êî"],"ascent":-63,"height":16},{"type":"bitmap","file":"mcc:_fonts/team_halloween/cyan_big.png","chars":["¯êì"],"ascent":-66,"height":16},{"type":"bitmap","file":"mcc:_fonts/team_halloween/cyan_glow.png","chars":["¯êÄ"],"ascent":-66,"height":16},{"type":"bitmap","file":"mcc:_fonts/team_halloween/cyan_moment.png","chars":["¯êÅ"],"ascent":-65,"height":8},{"type":"bitmap","file":"mcc:_fonts/team_halloween/cyan_spec.png","chars":["¯êÉ"],"ascent":-63,"height":16},{"type":"bitmap","file":"mcc:_fonts/team_halloween/cyan_spec_gray.png","chars":["¯êæ"],"ascent":-63,"height":16},{"type":"bitmap","file":"mcc:_fonts/team_halloween/green.png","chars":["¯êÆ"],"ascent":-66,"height":8},{"type":"bitmap","file":"mcc:_fonts/team_halloween/green_bar.png","chars":["¯êô"],"ascent":-63,"height":16},{"type":"bitmap","file":"mcc:_fonts/team_halloween/green_big.png","chars":["¯êö"],"ascent":-66,"height":16},{"type":"bitmap","file":"mcc:_fonts/team_halloween/green_glow.png","chars":["¯êò"],"ascent":-66,"height":16},{"type":"bitmap","file":"mcc:_fonts/team_halloween/green_moment.png","chars":["¯êû"],"ascent":-65,"height":8},{"type":"bitmap","file":"mcc:_fonts/team_halloween/green_spec.png","chars":["¯êù"],"ascent":-63,"height":16},{"type":"bitmap","file":"mcc:_fonts/team_halloween/green_spec_gray.png","chars":["¯êÿ"],"ascent":-63,"height":16},{"type":"bitmap","file":"mcc:_fonts/team_halloween/lime.png","chars":["¯êÖ"],"ascent":-66,"height":8},{"type":"bitmap","file":"mcc:_fonts/team_halloween/lime_bar.png","chars":["¯êÜ"],"ascent":-63,"height":16},{"type":"bitmap","file":"mcc:_fonts/team_halloween/lime_big.png","chars":["¯êø"],"ascent":-66,"height":16},{"type":"bitmap","file":"mcc:_fonts/team_halloween/lime_glow.png","chars":["¯ê£"],"ascent":-66,"height":16},{"type":"bitmap","file":"mcc:_fonts/team_halloween/lime_moment.png","chars":["¯êØ"],"ascent":-65,"height":8},{"type":"bitmap","file":"mcc:_fonts/team_halloween/lime_spec.png","chars":["¯ê×"],"ascent":-63,"height":16},{"type":"bitmap","file":"mcc:_fonts/team_halloween/lime_spec_gray.png","chars":["¯êƒ"],"ascent":-63,"height":16},{"type":"bitmap","file":"mcc:_fonts/team_halloween/orange.png","chars":["¯êá"],"ascent":-66,"height":8},{"type":"bitmap","file":"mcc:_fonts/team_halloween/orange_bar.png","chars":["¯êí"],"ascent":-63,"height":16},{"type":"bitmap","file":"mcc:_fonts/team_halloween/orange_big.png","chars":["¯êó"],"ascent":-66,"height":16},{"type":"bitmap","file":"mcc:_fonts/team_halloween/orange_glow.png","chars":["¯êú"],"ascent":-66,"height":16},{"type":"bitmap","file":"mcc:_fonts/team_halloween/orange_moment.png","chars":["¯êñ"],"ascent":-65,"height":8},{"type":"bitmap","file":"mcc:_fonts/team_halloween/orange_spec.png","chars":["¯êÑ"],"ascent":-63,"height":16},{"type":"bitmap","file":"mcc:_fonts/team_halloween/orange_spec_gray.png","chars":["¯êª"],"ascent":-63,"height":16},{"type":"bitmap","file":"mcc:_fonts/team_halloween/pink.png","chars":["¯êº"],"ascent":-66,"height":8},{"type":"bitmap","file":"mcc:_fonts/team_halloween/pink_bar.png","chars":["¯ê¿"],"ascent":-63,"height":16},{"type":"bitmap","file":"mcc:_fonts/team_halloween/pink_big.png","chars":["¯ê®"],"ascent":-66,"height":16},{"type":"bitmap","file":"mcc:_fonts/team_halloween/pink_glow.png","chars":["¯ê¬"],"ascent":-66,"height":16},{"type":"bitmap","file":"mcc:_fonts/team_halloween/pink_moment.png","chars":["¯ê½"],"ascent":-65,"height":8},{"type":"bitmap","file":"mcc:_fonts/team_halloween/pink_spec.png","chars":["¯ê¼"],"ascent":-63,"height":16},{"type":"bitmap","file":"mcc:_fonts/team_halloween/pink_spec_gray.png","chars":["¯ê¡"],"ascent":-63,"height":16},{"type":"bitmap","file":"mcc:_fonts/team_halloween/purple.png","chars":["¯ê«"],"ascent":-66,"height":8},{"type":"bitmap","file":"mcc:_fonts/team_halloween/purple_bar.png","chars":["¯ê»"],"ascent":-63,"height":16},{"type":"bitmap","file":"mcc:_fonts/team_halloween/purple_big.png","chars":["¯ê░"],"ascent":-66,"height":16},{"type":"bitmap","file":"mcc:_fonts/team_halloween/purple_glow.png","chars":["¯ê▒"],"ascent":-66,"height":16},{"type":"bitmap","file":"mcc:_fonts/team_halloween/purple_moment.png","chars":["¯ê▓"],"ascent":-65,"height":8},{"type":"bitmap","file":"mcc:_fonts/team_halloween/purple_spec.png","chars":["¯ê│"],"ascent":-63,"height":16},{"type":"bitmap","file":"mcc:_fonts/team_halloween/purple_spec_gray.png","chars":["¯ê┤"],"ascent":-63,"height":16},{"type":"bitmap","file":"mcc:_fonts/team_halloween/red.png","chars":["¯êÁ"],"ascent":-66,"height":8},{"type":"bitmap","file":"mcc:_fonts/team_halloween/red_bar.png","chars":["¯êÂ"],"ascent":-63,"height":16},{"type":"bitmap","file":"mcc:_fonts/team_halloween/red_big.png","chars":["¯êÀ"],"ascent":-66,"height":16},{"type":"bitmap","file":"mcc:_fonts/team_halloween/red_glow.png","chars":["¯ê©"],"ascent":-66,"height":16},{"type":"bitmap","file":"mcc:_fonts/team_halloween/red_moment.png","chars":["¯ê╣"],"ascent":-65,"height":8},{"type":"bitmap","file":"mcc:_fonts/team_halloween/red_spec.png","chars":["¯ê║"],"ascent":-63,"height":16},{"type":"bitmap","file":"mcc:_fonts/team_halloween/red_spec_gray.png","chars":["¯ê╗"],"ascent":-63,"height":16},{"type":"bitmap","file":"mcc:_fonts/team_halloween/spectator.png","chars":["¯ê╝"],"ascent":-66,"height":8},{"type":"bitmap","file":"mcc:_fonts/team_halloween/spectators.png","chars":["¯ê¢"],"ascent":-66,"height":8},{"type":"bitmap","file":"mcc:_fonts/team_halloween/yellow.png","chars":["¯ê¥"],"ascent":-66,"height":8},{"type":"bitmap","file":"mcc:_fonts/team_halloween/yellow_bar.png","chars":["¯ê┐"],"ascent":-63,"height":16},{"type":"bitmap","file":"mcc:_fonts/team_halloween/yellow_big.png","chars":["¯ëÇ"],"ascent":-66,"height":16},{"type":"bitmap","file":"mcc:_fonts/team_halloween/yellow_glow.png","chars":["¯ëü"],"ascent":-66,"height":16},{"type":"bitmap","file":"mcc:_fonts/team_halloween/yellow_moment.png","chars":["¯ëé"],"ascent":-65,"height":8},{"type":"bitmap","file":"mcc:_fonts/team_halloween/yellow_spec.png","chars":["¯ëâ"],"ascent":-63,"height":16},{"type":"bitmap","file":"mcc:_fonts/team_halloween/yellow_spec_gray.png","chars":["¯ëä"],"ascent":-63,"height":16},{"type":"bitmap","file":"mcc:_fonts/team_winter/aqua.png","chars":["¯ëà"],"ascent":-66,"height":8},{"type":"bitmap","file":"mcc:_fonts/team_winter/aqua_bar.png","chars":["¯ëå"],"ascent":-63,"height":16},{"type":"bitmap","file":"mcc:_fonts/team_winter/aqua_big.png","chars":["¯ëç"],"ascent":-66,"height":16},{"type":"bitmap","file":"mcc:_fonts/team_winter/aqua_glow.png","chars":["¯ëê"],"ascent":-66,"height":16},{"type":"bitmap","file":"mcc:_fonts/team_winter/aqua_moment.png","chars":["¯ëë"],"ascent":-65,"height":8},{"type":"bitmap","file":"mcc:_fonts/team_winter/aqua_spec.png","chars":["¯ëè"],"ascent":-63,"height":16},{"type":"bitmap","file":"mcc:_fonts/team_winter/aqua_spec_gray.png","chars":["¯ëï"],"ascent":-63,"height":16},{"type":"bitmap","file":"mcc:_fonts/team_winter/blue.png","chars":["¯ëî"],"ascent":-66,"height":8},{"type":"bitmap","file":"mcc:_fonts/team_winter/blue_bar.png","chars":["¯ëì"],"ascent":-63,"height":16},{"type":"bitmap","file":"mcc:_fonts/team_winter/blue_big.png","chars":["¯ëÄ"],"ascent":-66,"height":16},{"type":"bitmap","file":"mcc:_fonts/team_winter/blue_glow.png","chars":["¯ëÅ"],"ascent":-66,"height":16},{"type":"bitmap","file":"mcc:_fonts/team_winter/blue_moment.png","chars":["¯ëÉ"],"ascent":-65,"height":8},{"type":"bitmap","file":"mcc:_fonts/team_winter/blue_spec.png","chars":["¯ëæ"],"ascent":-63,"height":16},{"type":"bitmap","file":"mcc:_fonts/team_winter/blue_spec_gray.png","chars":["¯ëÆ"],"ascent":-63,"height":16},{"type":"bitmap","file":"mcc:_fonts/team_winter/cyan.png","chars":["¯ëô"],"ascent":-66,"height":8},{"type":"bitmap","file":"mcc:_fonts/team_winter/cyan_bar.png","chars":["¯ëö"],"ascent":-63,"height":16},{"type":"bitmap","file":"mcc:_fonts/team_winter/cyan_big.png","chars":["¯ëò"],"ascent":-66,"height":16},{"type":"bitmap","file":"mcc:_fonts/team_winter/cyan_glow.png","chars":["¯ëû"],"ascent":-66,"height":16},{"type":"bitmap","file":"mcc:_fonts/team_winter/cyan_moment.png","chars":["¯ëù"],"ascent":-65,"height":8},{"type":"bitmap","file":"mcc:_fonts/team_winter/cyan_spec.png","chars":["¯ëÿ"],"ascent":-63,"height":16},{"type":"bitmap","file":"mcc:_fonts/team_winter/cyan_spec_gray.png","chars":["¯ëÖ"],"ascent":-63,"height":16},{"type":"bitmap","file":"mcc:_fonts/team_winter/green.png","chars":["¯ëÜ"],"ascent":-66,"height":8},{"type":"bitmap","file":"mcc:_fonts/team_winter/green_bar.png","chars":["¯ëø"],"ascent":-63,"height":16},{"type":"bitmap","file":"mcc:_fonts/team_winter/green_big.png","chars":["¯ë£"],"ascent":-66,"height":16},{"type":"bitmap","file":"mcc:_fonts/team_winter/green_glow.png","chars":["¯ëØ"],"ascent":-66,"height":16},{"type":"bitmap","file":"mcc:_fonts/team_winter/green_moment.png","chars":["¯ë×"],"ascent":-65,"height":8},{"type":"bitmap","file":"mcc:_fonts/team_winter/green_spec.png","chars":["¯ëƒ"],"ascent":-63,"height":16},{"type":"bitmap","file":"mcc:_fonts/team_winter/green_spec_gray.png","chars":["¯ëá"],"ascent":-63,"height":16},{"type":"bitmap","file":"mcc:_fonts/team_winter/lime.png","chars":["¯ëí"],"ascent":-66,"height":8},{"type":"bitmap","file":"mcc:_fonts/team_winter/lime_bar.png","chars":["¯ëó"],"ascent":-63,"height":16},{"type":"bitmap","file":"mcc:_fonts/team_winter/lime_big.png","chars":["¯ëú"],"ascent":-66,"height":16},{"type":"bitmap","file":"mcc:_fonts/team_winter/lime_glow.png","chars":["¯ëñ"],"ascent":-66,"height":16},{"type":"bitmap","file":"mcc:_fonts/team_winter/lime_moment.png","chars":["¯ëÑ"],"ascent":-65,"height":8},{"type":"bitmap","file":"mcc:_fonts/team_winter/lime_spec.png","chars":["¯ëª"],"ascent":-63,"height":16},{"type":"bitmap","file":"mcc:_fonts/team_winter/lime_spec_gray.png","chars":["¯ëº"],"ascent":-63,"height":16},{"type":"bitmap","file":"mcc:_fonts/team_winter/orange.png","chars":["¯ë¿"],"ascent":-66,"height":8},{"type":"bitmap","file":"mcc:_fonts/team_winter/orange_bar.png","chars":["¯ë®"],"ascent":-63,"height":16},{"type":"bitmap","file":"mcc:_fonts/team_winter/orange_big.png","chars":["¯ë¬"],"ascent":-66,"height":16},{"type":"bitmap","file":"mcc:_fonts/team_winter/orange_glow.png","chars":["¯ë½"],"ascent":-66,"height":16},{"type":"bitmap","file":"mcc:_fonts/team_winter/orange_moment.png","chars":["¯ë¼"],"ascent":-65,"height":8},{"type":"bitmap","file":"mcc:_fonts/team_winter/orange_spec.png","chars":["¯ë¡"],"ascent":-63,"height":16},{"type":"bitmap","file":"mcc:_fonts/team_winter/orange_spec_gray.png","chars":["¯ë«"],"ascent":-63,"height":16},{"type":"bitmap","file":"mcc:_fonts/team_winter/pink.png","chars":["¯ë»"],"ascent":-66,"height":8},{"type":"bitmap","file":"mcc:_fonts/team_winter/pink_bar.png","chars":["¯ë░"],"ascent":-63,"height":16},{"type":"bitmap","file":"mcc:_fonts/team_winter/pink_big.png","chars":["¯ë▒"],"ascent":-66,"height":16},{"type":"bitmap","file":"mcc:_fonts/team_winter/pink_glow.png","chars":["¯ë▓"],"ascent":-66,"height":16},{"type":"bitmap","file":"mcc:_fonts/team_winter/pink_moment.png","chars":["¯ë│"],"ascent":-65,"height":8},{"type":"bitmap","file":"mcc:_fonts/team_winter/pink_spec.png","chars":["¯ë┤"],"ascent":-63,"height":16},{"type":"bitmap","file":"mcc:_fonts/team_winter/pink_spec_gray.png","chars":["¯ëÁ"],"ascent":-63,"height":16},{"type":"bitmap","file":"mcc:_fonts/team_winter/purple.png","chars":["¯ëÂ"],"ascent":-66,"height":8},{"type":"bitmap","file":"mcc:_fonts/team_winter/purple_bar.png","chars":["¯ëÀ"],"ascent":-63,"height":16},{"type":"bitmap","file":"mcc:_fonts/team_winter/purple_big.png","chars":["¯ë©"],"ascent":-66,"height":16},{"type":"bitmap","file":"mcc:_fonts/team_winter/purple_glow.png","chars":["¯ë╣"],"ascent":-66,"height":16},{"type":"bitmap","file":"mcc:_fonts/team_winter/purple_moment.png","chars":["¯ë║"],"ascent":-65,"height":8},{"type":"bitmap","file":"mcc:_fonts/team_winter/purple_spec.png","chars":["¯ë╗"],"ascent":-63,"height":16},{"type":"bitmap","file":"mcc:_fonts/team_winter/purple_spec_gray.png","chars":["¯ë╝"],"ascent":-63,"height":16},{"type":"bitmap","file":"mcc:_fonts/team_winter/red.png","chars":["¯ë¢"],"ascent":-66,"height":8},{"type":"bitmap","file":"mcc:_fonts/team_winter/red_bar.png","chars":["¯ë¥"],"ascent":-63,"height":16},{"type":"bitmap","file":"mcc:_fonts/team_winter/red_big.png","chars":["¯ë┐"],"ascent":-66,"height":16},{"type":"bitmap","file":"mcc:_fonts/team_winter/red_glow.png","chars":["¯èÇ"],"ascent":-66,"height":16},{"type":"bitmap","file":"mcc:_fonts/team_winter/red_moment.png","chars":["¯èü"],"ascent":-65,"height":8},{"type":"bitmap","file":"mcc:_fonts/team_winter/red_spec.png","chars":["¯èé"],"ascent":-63,"height":16},{"type":"bitmap","file":"mcc:_fonts/team_winter/red_spec_gray.png","chars":["¯èâ"],"ascent":-63,"height":16},{"type":"bitmap","file":"mcc:_fonts/team_winter/spectator.png","chars":["¯èä"],"ascent":-66,"height":8},{"type":"bitmap","file":"mcc:_fonts/team_winter/spectators.png","chars":["¯èà"],"ascent":-66,"height":8},{"type":"bitmap","file":"mcc:_fonts/team_winter/yellow.png","chars":["¯èå"],"ascent":-66,"height":8},{"type":"bitmap","file":"mcc:_fonts/team_winter/yellow_bar.png","chars":["¯èç"],"ascent":-63,"height":16},{"type":"bitmap","file":"mcc:_fonts/team_winter/yellow_big.png","chars":["¯èê"],"ascent":-66,"height":16},{"type":"bitmap","file":"mcc:_fonts/team_winter/yellow_glow.png","chars":["¯èë"],"ascent":-66,"height":16},{"type":"bitmap","file":"mcc:_fonts/team_winter/yellow_moment.png","chars":["¯èè"],"ascent":-65,"height":8},{"type":"bitmap","file":"mcc:_fonts/team_winter/yellow_spec.png","chars":["¯èï"],"ascent":-63,"height":16},{"type":"bitmap","file":"mcc:_fonts/team_winter/yellow_spec_gray.png","chars":["¯èî"],"ascent":-63,"height":16},{"type":"bitmap","file":"mcc:_fonts/tick_small.png","chars":["¯èì"],"ascent":-66,"height":8},{"type":"bitmap","file":"mcc:_fonts/time.png","chars":["¯èÄ"],"ascent":-66,"height":8},{"type":"bitmap","file":"mcc:_fonts/time_offset_53.png","chars":["¯èÅ"],"ascent":-118,"height":8},{"type":"bitmap","file":"mcc:_fonts/token/attuned.png","chars":["¯èÉ"],"ascent":-66,"height":8},{"type":"bitmap","file":"mcc:_fonts/token/legacy.png","chars":["¯èæ"],"ascent":-66,"height":8},{"type":"bitmap","file":"mcc:_fonts/token/seasonal.png","chars":["¯èÆ"],"ascent":-66,"height":8},{"type":"bitmap","file":"mcc:_fonts/token/standard.png","chars":["¯èô"],"ascent":-66,"height":8},{"type":"bitmap","file":"mcc:_fonts/token_attuned.png","chars":["¯èö"],"ascent":-66,"height":8},{"type":"bitmap","file":"mcc:_fonts/token_boosted.png","chars":["¯èò"],"ascent":-66,"height":8},{"type":"bitmap","file":"mcc:_fonts/token_legacy.png","chars":["¯èû"],"ascent":-66,"height":8},{"type":"bitmap","file":"mcc:_fonts/token_s2.png","chars":["¯èù"],"ascent":-66,"height":8},{"type":"bitmap","file":"mcc:_fonts/token_seasonal.png","chars":["¯èÿ"],"ascent":-66,"height":8},{"type":"bitmap","file":"mcc:_fonts/token_standard.png","chars":["¯èÖ"],"ascent":-66,"height":8},{"type":"bitmap","file":"mcc:_fonts/token_ultimate.png","chars":["¯èÜ"],"ascent":-66,"height":8},{"type":"bitmap","file":"mcc:_fonts/tooltips/accessory.png","chars":["¯èø"],"ascent":-66,"height":9},{"type":"bitmap","file":"mcc:_fonts/tooltips/achievement.png","chars":["¯è£"],"ascent":-66,"height":64},{"type":"bitmap","file":"mcc:_fonts/tooltips/augment.png","chars":["¯èØ"],"ascent":-66,"height":64},{"type":"bitmap","file":"mcc:_fonts/tooltips/aura.png","chars":["¯è×"],"ascent":-66,"height":9},{"type":"bitmap","file":"mcc:_fonts/tooltips/back.png","chars":["¯èƒ"],"ascent":-66,"height":9},{"type":"bitmap","file":"mcc:_fonts/tooltips/badge.png","chars":["¯èá"],"ascent":-66,"height":9},{"type":"bitmap","file":"mcc:_fonts/tooltips/blueprint.png","chars":["¯èí"],"ascent":-66,"height":9},{"type":"bitmap","file":"mcc:_fonts/tooltips/bundle.png","chars":["¯èó"],"ascent":-66,"height":9},{"type":"bitmap","file":"mcc:_fonts/tooltips/common.png","chars":["¯èú"],"ascent":-66,"height":9},{"type":"bitmap","file":"mcc:_fonts/tooltips/component.png","chars":["¯èñ"],"ascent":-66,"height":9},{"type":"bitmap","file":"mcc:_fonts/tooltips/consumable.png","chars":["¯èÑ"],"ascent":-66,"height":9},{"type":"bitmap","file":"mcc:_fonts/tooltips/crab.png","chars":["¯èª"],"ascent":-66,"height":9},{"type":"bitmap","file":"mcc:_fonts/tooltips/currency.png","chars":["¯èº"],"ascent":-66,"height":9},{"type":"bitmap","file":"mcc:_fonts/tooltips/daily_quest.png","chars":["¯è¿"],"ascent":-66,"height":9},{"type":"bitmap","file":"mcc:_fonts/tooltips/epic.png","chars":["¯è®"],"ascent":-66,"height":9},{"type":"bitmap","file":"mcc:_fonts/tooltips/faction.png","chars":["¯è¬"],"ascent":-66,"height":9},{"type":"bitmap","file":"mcc:_fonts/tooltips/fish.png","chars":["¯è½"],"ascent":-66,"height":9},{"type":"bitmap","file":"mcc:_fonts/tooltips/fishing_rod.png","chars":["¯è¼"],"ascent":-66,"height":9},{"type":"bitmap","file":"mcc:_fonts/tooltips/furniture.png","chars":["¯è¡"],"ascent":-66,"height":9},{"type":"bitmap","file":"mcc:_fonts/tooltips/gadget.png","chars":["¯è«"],"ascent":-66,"height":9},{"type":"bitmap","file":"mcc:_fonts/tooltips/gearstone.png","chars":["¯è»"],"ascent":-66,"height":64},{"type":"bitmap","file":"mcc:_fonts/tooltips/hair.png","chars":["¯è░"],"ascent":-66,"height":9},{"type":"bitmap","file":"mcc:_fonts/tooltips/hat.png","chars":["¯è▒"],"ascent":-66,"height":9},{"type":"bitmap","file":"mcc:_fonts/tooltips/heart.png","chars":["¯è▓"],"ascent":-66,"height":9},{"type":"bitmap","file":"mcc:_fonts/tooltips/item.png","chars":["¯è│"],"ascent":-66,"height":9},{"type":"bitmap","file":"mcc:_fonts/tooltips/legendary.png","chars":["¯è┤"],"ascent":-66,"height":9},{"type":"bitmap","file":"mcc:_fonts/tooltips/limited.png","chars":["¯èÁ"],"ascent":-66,"height":9},{"type":"bitmap","file":"mcc:_fonts/tooltips/material.png","chars":["¯èÂ"],"ascent":-66,"height":9},{"type":"bitmap","file":"mcc:_fonts/tooltips/mount.png","chars":["¯èÀ"],"ascent":-66,"height":64},{"type":"bitmap","file":"mcc:_fonts/tooltips/mythic.png","chars":["¯è©"],"ascent":-66,"height":9},{"type":"bitmap","file":"mcc:_fonts/tooltips/openable.png","chars":["¯è╣"],"ascent":-66,"height":9},{"type":"bitmap","file":"mcc:_fonts/tooltips/pass_meter.png","chars":["¯è║"],"ascent":-66,"height":9},{"type":"bitmap","file":"mcc:_fonts/tooltips/pet.png","chars":["¯è╗"],"ascent":-66,"height":64},{"type":"bitmap","file":"mcc:_fonts/tooltips/prismatic.png","chars":["¯è╝"],"ascent":-66,"height":9},{"type":"bitmap","file":"mcc:_fonts/tooltips/projectile.png","chars":["¯è¢"],"ascent":-66,"height":9},{"type":"bitmap","file":"mcc:_fonts/tooltips/quest_meter.png","chars":["¯è¥"],"ascent":-66,"height":9},{"type":"bitmap","file":"mcc:_fonts/tooltips/quest_scroll.png","chars":["¯è┐"],"ascent":-66,"height":9},{"type":"bitmap","file":"mcc:_fonts/tooltips/ranged_weapon.png","chars":["¯ïÇ"],"ascent":-66,"height":9},{"type":"bitmap","file":"mcc:_fonts/tooltips/rare.png","chars":["¯ïü"],"ascent":-66,"height":9},{"type":"bitmap","file":"mcc:_fonts/tooltips/seasonal.png","chars":["¯ïé"],"ascent":-66,"height":9},{"type":"bitmap","file":"mcc:_fonts/tooltips/squidtek.png","chars":["¯ïâ"],"ascent":-66,"height":9},{"type":"bitmap","file":"mcc:_fonts/tooltips/sunken_quest.png","chars":["¯ïä"],"ascent":-66,"height":9},{"type":"bitmap","file":"mcc:_fonts/tooltips/trail.png","chars":["¯ïà"],"ascent":-66,"height":9},{"type":"bitmap","file":"mcc:_fonts/tooltips/uncommon.png","chars":["¯ïå"],"ascent":-66,"height":9},{"type":"bitmap","file":"mcc:_fonts/tooltips/variant.png","chars":["¯ïç"],"ascent":-66,"height":9},{"type":"bitmap","file":"mcc:_fonts/tooltips/veteran.png","chars":["¯ïê"],"ascent":-66,"height":9},{"type":"bitmap","file":"mcc:_fonts/tooltips/weapon.png","chars":["¯ïë"],"ascent":-66,"height":9},{"type":"bitmap","file":"mcc:_fonts/tooltips/weekly_quest.png","chars":["¯ïè"],"ascent":-66,"height":9},{"type":"bitmap","file":"mcc:_fonts/trail_small.png","chars":["¯ïï"],"ascent":-66,"height":8},{"type":"bitmap","file":"mcc:_fonts/unknown.png","chars":["¯ïî"],"ascent":-66,"height":8},{"type":"bitmap","file":"mcc:_fonts/wardrobe.png","chars":["¯ïì"],"ascent":-66,"height":8},{"type":"bitmap","file":"mcc:_fonts/warning_blue.png","chars":["¯ïÄ"],"ascent":-66,"height":8},{"type":"bitmap","file":"mcc:_fonts/warning_blue_offset_53.png","chars":["¯ïÅ"],"ascent":-118,"height":8},{"type":"bitmap","file":"mcc:_fonts/warning_orange.png","chars":["¯ïÉ"],"ascent":-66,"height":8},{"type":"bitmap","file":"mcc:_fonts/warning_orange_offset_53.png","chars":["¯ïæ"],"ascent":-118,"height":8},{"type":"bitmap","file":"mcc:_fonts/warning_purple.png","chars":["¯ïÆ"],"ascent":-66,"height":8},{"type":"bitmap","file":"mcc:_fonts/warning_red.png","chars":["¯ïô"],"ascent":-66,"height":8},{"type":"bitmap","file":"mcc:_fonts/warning_red_offset_53.png","chars":["¯ïö"],"ascent":-118,"height":8},{"type":"bitmap","file":"mcc:_fonts/warning_yellow.png","chars":["¯ïò"],"ascent":-66,"height":8},{"type":"bitmap","file":"mcc:_fonts/wetness.png","chars":["¯ïû"],"ascent":-66,"height":9},{"type":"bitmap","file":"mcc:_fonts/winner.png","chars":["¯ïù"],"ascent":-66,"height":8},{"type":"bitmap","file":"mcc:_fonts/xp_bonus.png","chars":["¯ïÿ"],"ascent":-126,"height":9}]}